{
  "_schema_설명": "43개 읍면동(한림읍 포함) 전체 팀 인스턴스. emd-master-data.json/hallim-data.json의 팀구성 필드를 원자료로 자동 생성(2026-07-10) — 읍/면 5팀(총무·민원·산업·주민복지·찾아가는복지), 동 4팀(산업팀 없음). (emd_code, team_code)로 매칭.",
  "팀목록": [
    {
      "emd_code": "SP-EMD-AEWOL",
      "team_code": "general",
      "도이름": "제주특별자치도",
      "시이름": "제주시",
      "읍면동이름": "애월읍",
      "팀이름": "총무팀",
      "입력_문구": "민방위, 청소·환경정비, 이륜차 민원, 청사 관리 관련 접수·신청",
      "출력_문구": "민방위 훈련·청소환경정비 처리 결과, 청사 이용 안내",
      "콜센터명": "제주콜센터",
      "콜센터번호": "TBD",
      "콜센터운영시간": "평일 09:00~18:00 (점심 12:00~13:00), 무인민원발급기 24시간"
    },
    {
      "emd_code": "SP-EMD-AEWOL",
      "team_code": "civil",
      "도이름": "제주특별자치도",
      "시이름": "제주시",
      "읍면동이름": "애월읍",
      "팀이름": "민원팀",
      "입력_문구": "주민등록등초본, 가족관계등록, 인감증명 등 제증명 발급 관련 접수·신청",
      "출력_문구": "즉시발급 증명서(등초본·인감증명 등)",
      "콜센터명": "제주콜센터",
      "콜센터번호": "TBD",
      "콜센터운영시간": "평일 09:00~18:00 (점심 12:00~13:00), 무인민원발급기 24시간"
    },
    {
      "emd_code": "SP-EMD-AEWOL",
      "team_code": "industry",
      "도이름": "제주특별자치도",
      "시이름": "제주시",
      "읍면동이름": "애월읍",
      "팀이름": "산업팀",
      "입력_문구": "농업경영체 등록, 영농지원, 지역 주력산업 현장 지원 관련 접수·신청",
      "출력_문구": "접수증(최종 등록·지원 결정은 시청 소관 부서에서 확정)",
      "콜센터명": "제주콜센터",
      "콜센터번호": "TBD",
      "콜센터운영시간": "평일 09:00~18:00 (점심 12:00~13:00), 무인민원발급기 24시간"
    },
    {
      "emd_code": "SP-EMD-AEWOL",
      "team_code": "welfare",
      "도이름": "제주특별자치도",
      "시이름": "제주시",
      "읍면동이름": "애월읍",
      "팀이름": "주민복지팀",
      "입력_문구": "기초생활수급·기초연금 접수, 보훈 접수(1차 접수, 최종 심사는 시청 소관) 관련 접수·신청",
      "출력_문구": "복지 신청 접수증(지급결정은 시청 복지위생국에서 확정)",
      "콜센터명": "제주콜센터",
      "콜센터번호": "TBD",
      "콜센터운영시간": "평일 09:00~18:00 (점심 12:00~13:00), 무인민원발급기 24시간"
    },
    {
      "emd_code": "SP-EMD-AEWOL",
      "team_code": "outreach",
      "도이름": "제주특별자치도",
      "시이름": "제주시",
      "읍면동이름": "애월읍",
      "팀이름": "찾아가는복지팀",
      "입력_문구": "복지 사각지대 발굴, 방문 상담 관련 접수·신청",
      "출력_문구": "방문상담 결과, 복지서비스 연계",
      "콜센터명": "제주콜센터",
      "콜센터번호": "TBD",
      "콜센터운영시간": "평일 09:00~18:00 (점심 12:00~13:00), 무인민원발급기 24시간"
    },
    {
      "emd_code": "SP-EMD-JOCHEON",
      "team_code": "general",
      "도이름": "제주특별자치도",
      "시이름": "제주시",
      "읍면동이름": "조천읍",
      "팀이름": "총무팀",
      "입력_문구": "민방위, 청소·환경정비, 이륜차 민원, 청사 관리 관련 접수·신청",
      "출력_문구": "민방위 훈련·청소환경정비 처리 결과, 청사 이용 안내",
      "콜센터명": "제주콜센터",
      "콜센터번호": "TBD",
      "콜센터운영시간": "평일 09:00~18:00 (점심 12:00~13:00), 무인민원발급기 24시간"
    },
    {
      "emd_code": "SP-EMD-JOCHEON",
      "team_code": "civil",
      "도이름": "제주특별자치도",
      "시이름": "제주시",
      "읍면동이름": "조천읍",
      "팀이름": "민원팀",
      "입력_문구": "주민등록등초본, 가족관계등록, 인감증명 등 제증명 발급 관련 접수·신청",
      "출력_문구": "즉시발급 증명서(등초본·인감증명 등)",
      "콜센터명": "제주콜센터",
      "콜센터번호": "TBD",
      "콜센터운영시간": "평일 09:00~18:00 (점심 12:00~13:00), 무인민원발급기 24시간"
    },
    {
      "emd_code": "SP-EMD-JOCHEON",
      "team_code": "industry",
      "도이름": "제주특별자치도",
      "시이름": "제주시",
      "읍면동이름": "조천읍",
      "팀이름": "산업팀",
      "입력_문구": "농업경영체 등록, 영농지원, 지역 주력산업 현장 지원 관련 접수·신청",
      "출력_문구": "접수증(최종 등록·지원 결정은 시청 소관 부서에서 확정)",
      "콜센터명": "제주콜센터",
      "콜센터번호": "TBD",
      "콜센터운영시간": "평일 09:00~18:00 (점심 12:00~13:00), 무인민원발급기 24시간"
    },
    {
      "emd_code": "SP-EMD-JOCHEON",
      "team_code": "welfare",
      "도이름": "제주특별자치도",
      "시이름": "제주시",
      "읍면동이름": "조천읍",
      "팀이름": "주민복지팀",
      "입력_문구": "기초생활수급·기초연금 접수, 보훈 접수(1차 접수, 최종 심사는 시청 소관) 관련 접수·신청",
      "출력_문구": "복지 신청 접수증(지급결정은 시청 복지위생국에서 확정)",
      "콜센터명": "제주콜센터",
      "콜센터번호": "TBD",
      "콜센터운영시간": "평일 09:00~18:00 (점심 12:00~13:00), 무인민원발급기 24시간"
    },
    {
      "emd_code": "SP-EMD-JOCHEON",
      "team_code": "outreach",
      "도이름": "제주특별자치도",
      "시이름": "제주시",
      "읍면동이름": "조천읍",
      "팀이름": "찾아가는복지팀",
      "입력_문구": "복지 사각지대 발굴, 방문 상담 관련 접수·신청",
      "출력_문구": "방문상담 결과, 복지서비스 연계",
      "콜센터명": "제주콜센터",
      "콜센터번호": "TBD",
      "콜센터운영시간": "평일 09:00~18:00 (점심 12:00~13:00), 무인민원발급기 24시간"
    },
    {
      "emd_code": "SP-EMD-GUJWA",
      "team_code": "general",
      "도이름": "제주특별자치도",
      "시이름": "제주시",
      "읍면동이름": "구좌읍",
      "팀이름": "총무팀",
      "입력_문구": "민방위, 청소·환경정비, 이륜차 민원, 청사 관리 관련 접수·신청",
      "출력_문구": "민방위 훈련·청소환경정비 처리 결과, 청사 이용 안내",
      "콜센터명": "제주콜센터",
      "콜센터번호": "TBD",
      "콜센터운영시간": "평일 09:00~18:00 (점심 12:00~13:00), 무인민원발급기 24시간"
    },
    {
      "emd_code": "SP-EMD-GUJWA",
      "team_code": "civil",
      "도이름": "제주특별자치도",
      "시이름": "제주시",
      "읍면동이름": "구좌읍",
      "팀이름": "민원팀",
      "입력_문구": "주민등록등초본, 가족관계등록, 인감증명 등 제증명 발급 관련 접수·신청",
      "출력_문구": "즉시발급 증명서(등초본·인감증명 등)",
      "콜센터명": "제주콜센터",
      "콜센터번호": "TBD",
      "콜센터운영시간": "평일 09:00~18:00 (점심 12:00~13:00), 무인민원발급기 24시간"
    },
    {
      "emd_code": "SP-EMD-GUJWA",
      "team_code": "industry",
      "도이름": "제주특별자치도",
      "시이름": "제주시",
      "읍면동이름": "구좌읍",
      "팀이름": "산업팀",
      "입력_문구": "농업경영체 등록, 영농지원, 지역 주력산업 현장 지원 관련 접수·신청",
      "출력_문구": "접수증(최종 등록·지원 결정은 시청 소관 부서에서 확정)",
      "콜센터명": "제주콜센터",
      "콜센터번호": "TBD",
      "콜센터운영시간": "평일 09:00~18:00 (점심 12:00~13:00), 무인민원발급기 24시간"
    },
    {
      "emd_code": "SP-EMD-GUJWA",
      "team_code": "welfare",
      "도이름": "제주특별자치도",
      "시이름": "제주시",
      "읍면동이름": "구좌읍",
      "팀이름": "주민복지팀",
      "입력_문구": "기초생활수급·기초연금 접수, 보훈 접수(1차 접수, 최종 심사는 시청 소관) 관련 접수·신청",
      "출력_문구": "복지 신청 접수증(지급결정은 시청 복지위생국에서 확정)",
      "콜센터명": "제주콜센터",
      "콜센터번호": "TBD",
      "콜센터운영시간": "평일 09:00~18:00 (점심 12:00~13:00), 무인민원발급기 24시간"
    },
    {
      "emd_code": "SP-EMD-GUJWA",
      "team_code": "outreach",
      "도이름": "제주특별자치도",
      "시이름": "제주시",
      "읍면동이름": "구좌읍",
      "팀이름": "찾아가는복지팀",
      "입력_문구": "복지 사각지대 발굴, 방문 상담 관련 접수·신청",
      "출력_문구": "방문상담 결과, 복지서비스 연계",
      "콜센터명": "제주콜센터",
      "콜센터번호": "TBD",
      "콜센터운영시간": "평일 09:00~18:00 (점심 12:00~13:00), 무인민원발급기 24시간"
    },
    {
      "emd_code": "SP-EMD-HANGYEONG",
      "team_code": "general",
      "도이름": "제주특별자치도",
      "시이름": "제주시",
      "읍면동이름": "한경면",
      "팀이름": "총무팀",
      "입력_문구": "민방위, 청소·환경정비, 이륜차 민원, 청사 관리 관련 접수·신청",
      "출력_문구": "민방위 훈련·청소환경정비 처리 결과, 청사 이용 안내",
      "콜센터명": "제주콜센터",
      "콜센터번호": "TBD",
      "콜센터운영시간": "평일 09:00~18:00 (점심 12:00~13:00), 무인민원발급기 24시간"
    },
    {
      "emd_code": "SP-EMD-HANGYEONG",
      "team_code": "civil",
      "도이름": "제주특별자치도",
      "시이름": "제주시",
      "읍면동이름": "한경면",
      "팀이름": "민원팀",
      "입력_문구": "주민등록등초본, 가족관계등록, 인감증명 등 제증명 발급 관련 접수·신청",
      "출력_문구": "즉시발급 증명서(등초본·인감증명 등)",
      "콜센터명": "제주콜센터",
      "콜센터번호": "TBD",
      "콜센터운영시간": "평일 09:00~18:00 (점심 12:00~13:00), 무인민원발급기 24시간"
    },
    {
      "emd_code": "SP-EMD-HANGYEONG",
      "team_code": "industry",
      "도이름": "제주특별자치도",
      "시이름": "제주시",
      "읍면동이름": "한경면",
      "팀이름": "산업팀",
      "입력_문구": "농업경영체 등록, 영농지원, 지역 주력산업 현장 지원 관련 접수·신청",
      "출력_문구": "접수증(최종 등록·지원 결정은 시청 소관 부서에서 확정)",
      "콜센터명": "제주콜센터",
      "콜센터번호": "TBD",
      "콜센터운영시간": "평일 09:00~18:00 (점심 12:00~13:00), 무인민원발급기 24시간"
    },
    {
      "emd_code": "SP-EMD-HANGYEONG",
      "team_code": "welfare",
      "도이름": "제주특별자치도",
      "시이름": "제주시",
      "읍면동이름": "한경면",
      "팀이름": "주민복지팀",
      "입력_문구": "기초생활수급·기초연금 접수, 보훈 접수(1차 접수, 최종 심사는 시청 소관) 관련 접수·신청",
      "출력_문구": "복지 신청 접수증(지급결정은 시청 복지위생국에서 확정)",
      "콜센터명": "제주콜센터",
      "콜센터번호": "TBD",
      "콜센터운영시간": "평일 09:00~18:00 (점심 12:00~13:00), 무인민원발급기 24시간"
    },
    {
      "emd_code": "SP-EMD-HANGYEONG",
      "team_code": "outreach",
      "도이름": "제주특별자치도",
      "시이름": "제주시",
      "읍면동이름": "한경면",
      "팀이름": "찾아가는복지팀",
      "입력_문구": "복지 사각지대 발굴, 방문 상담 관련 접수·신청",
      "출력_문구": "방문상담 결과, 복지서비스 연계",
      "콜센터명": "제주콜센터",
      "콜센터번호": "TBD",
      "콜센터운영시간": "평일 09:00~18:00 (점심 12:00~13:00), 무인민원발급기 24시간"
    },
    {
      "emd_code": "SP-EMD-CHUJA",
      "team_code": "general",
      "도이름": "제주특별자치도",
      "시이름": "제주시",
      "읍면동이름": "추자면",
      "팀이름": "총무팀",
      "입력_문구": "민방위, 청소·환경정비, 이륜차 민원, 청사 관리 관련 접수·신청",
      "출력_문구": "민방위 훈련·청소환경정비 처리 결과, 청사 이용 안내",
      "콜센터명": "제주콜센터",
      "콜센터번호": "TBD",
      "콜센터운영시간": "평일 09:00~18:00 (점심 12:00~13:00), 무인민원발급기 24시간"
    },
    {
      "emd_code": "SP-EMD-CHUJA",
      "team_code": "civil",
      "도이름": "제주특별자치도",
      "시이름": "제주시",
      "읍면동이름": "추자면",
      "팀이름": "민원팀",
      "입력_문구": "주민등록등초본, 가족관계등록, 인감증명 등 제증명 발급 관련 접수·신청",
      "출력_문구": "즉시발급 증명서(등초본·인감증명 등)",
      "콜센터명": "제주콜센터",
      "콜센터번호": "TBD",
      "콜센터운영시간": "평일 09:00~18:00 (점심 12:00~13:00), 무인민원발급기 24시간"
    },
    {
      "emd_code": "SP-EMD-CHUJA",
      "team_code": "industry",
      "도이름": "제주특별자치도",
      "시이름": "제주시",
      "읍면동이름": "추자면",
      "팀이름": "산업팀",
      "입력_문구": "농업경영체 등록, 영농지원, 지역 주력산업 현장 지원 관련 접수·신청",
      "출력_문구": "접수증(최종 등록·지원 결정은 시청 소관 부서에서 확정)",
      "콜센터명": "제주콜센터",
      "콜센터번호": "TBD",
      "콜센터운영시간": "평일 09:00~18:00 (점심 12:00~13:00), 무인민원발급기 24시간"
    },
    {
      "emd_code": "SP-EMD-CHUJA",
      "team_code": "welfare",
      "도이름": "제주특별자치도",
      "시이름": "제주시",
      "읍면동이름": "추자면",
      "팀이름": "주민복지팀",
      "입력_문구": "기초생활수급·기초연금 접수, 보훈 접수(1차 접수, 최종 심사는 시청 소관) 관련 접수·신청",
      "출력_문구": "복지 신청 접수증(지급결정은 시청 복지위생국에서 확정)",
      "콜센터명": "제주콜센터",
      "콜센터번호": "TBD",
      "콜센터운영시간": "평일 09:00~18:00 (점심 12:00~13:00), 무인민원발급기 24시간"
    },
    {
      "emd_code": "SP-EMD-CHUJA",
      "team_code": "outreach",
      "도이름": "제주특별자치도",
      "시이름": "제주시",
      "읍면동이름": "추자면",
      "팀이름": "찾아가는복지팀",
      "입력_문구": "복지 사각지대 발굴, 방문 상담 관련 접수·신청",
      "출력_문구": "방문상담 결과, 복지서비스 연계",
      "콜센터명": "제주콜센터",
      "콜센터번호": "TBD",
      "콜센터운영시간": "평일 09:00~18:00 (점심 12:00~13:00), 무인민원발급기 24시간"
    },
    {
      "emd_code": "SP-EMD-UDO",
      "team_code": "general",
      "도이름": "제주특별자치도",
      "시이름": "제주시",
      "읍면동이름": "우도면",
      "팀이름": "총무팀",
      "입력_문구": "민방위, 청소·환경정비, 이륜차 민원, 청사 관리 관련 접수·신청",
      "출력_문구": "민방위 훈련·청소환경정비 처리 결과, 청사 이용 안내",
      "콜센터명": "제주콜센터",
      "콜센터번호": "TBD",
      "콜센터운영시간": "평일 09:00~18:00 (점심 12:00~13:00), 무인민원발급기 24시간"
    },
    {
      "emd_code": "SP-EMD-UDO",
      "team_code": "civil",
      "도이름": "제주특별자치도",
      "시이름": "제주시",
      "읍면동이름": "우도면",
      "팀이름": "민원팀",
      "입력_문구": "주민등록등초본, 가족관계등록, 인감증명 등 제증명 발급 관련 접수·신청",
      "출력_문구": "즉시발급 증명서(등초본·인감증명 등)",
      "콜센터명": "제주콜센터",
      "콜센터번호": "TBD",
      "콜센터운영시간": "평일 09:00~18:00 (점심 12:00~13:00), 무인민원발급기 24시간"
    },
    {
      "emd_code": "SP-EMD-UDO",
      "team_code": "industry",
      "도이름": "제주특별자치도",
      "시이름": "제주시",
      "읍면동이름": "우도면",
      "팀이름": "산업팀",
      "입력_문구": "농업경영체 등록, 영농지원, 지역 주력산업 현장 지원 관련 접수·신청",
      "출력_문구": "접수증(최종 등록·지원 결정은 시청 소관 부서에서 확정)",
      "콜센터명": "제주콜센터",
      "콜센터번호": "TBD",
      "콜센터운영시간": "평일 09:00~18:00 (점심 12:00~13:00), 무인민원발급기 24시간"
    },
    {
      "emd_code": "SP-EMD-UDO",
      "team_code": "welfare",
      "도이름": "제주특별자치도",
      "시이름": "제주시",
      "읍면동이름": "우도면",
      "팀이름": "주민복지팀",
      "입력_문구": "기초생활수급·기초연금 접수, 보훈 접수(1차 접수, 최종 심사는 시청 소관) 관련 접수·신청",
      "출력_문구": "복지 신청 접수증(지급결정은 시청 복지위생국에서 확정)",
      "콜센터명": "제주콜센터",
      "콜센터번호": "TBD",
      "콜센터운영시간": "평일 09:00~18:00 (점심 12:00~13:00), 무인민원발급기 24시간"
    },
    {
      "emd_code": "SP-EMD-UDO",
      "team_code": "outreach",
      "도이름": "제주특별자치도",
      "시이름": "제주시",
      "읍면동이름": "우도면",
      "팀이름": "찾아가는복지팀",
      "입력_문구": "복지 사각지대 발굴, 방문 상담 관련 접수·신청",
      "출력_문구": "방문상담 결과, 복지서비스 연계",
      "콜센터명": "제주콜센터",
      "콜센터번호": "TBD",
      "콜센터운영시간": "평일 09:00~18:00 (점심 12:00~13:00), 무인민원발급기 24시간"
    },
    {
      "emd_code": "SP-EMD-DAEJEONG",
      "team_code": "general",
      "도이름": "제주특별자치도",
      "시이름": "서귀포시",
      "읍면동이름": "대정읍",
      "팀이름": "총무팀",
      "입력_문구": "민방위, 청소·환경정비, 이륜차 민원, 청사 관리 관련 접수·신청",
      "출력_문구": "민방위 훈련·청소환경정비 처리 결과, 청사 이용 안내",
      "콜센터명": "제주콜센터",
      "콜센터번호": "TBD",
      "콜센터운영시간": "평일 09:00~18:00 (점심 12:00~13:00), 무인민원발급기 24시간"
    },
    {
      "emd_code": "SP-EMD-DAEJEONG",
      "team_code": "civil",
      "도이름": "제주특별자치도",
      "시이름": "서귀포시",
      "읍면동이름": "대정읍",
      "팀이름": "민원팀",
      "입력_문구": "주민등록등초본, 가족관계등록, 인감증명 등 제증명 발급 관련 접수·신청",
      "출력_문구": "즉시발급 증명서(등초본·인감증명 등)",
      "콜센터명": "제주콜센터",
      "콜센터번호": "TBD",
      "콜센터운영시간": "평일 09:00~18:00 (점심 12:00~13:00), 무인민원발급기 24시간"
    },
    {
      "emd_code": "SP-EMD-DAEJEONG",
      "team_code": "industry",
      "도이름": "제주특별자치도",
      "시이름": "서귀포시",
      "읍면동이름": "대정읍",
      "팀이름": "산업팀",
      "입력_문구": "농업경영체 등록, 영농지원, 지역 주력산업 현장 지원 관련 접수·신청",
      "출력_문구": "접수증(최종 등록·지원 결정은 시청 소관 부서에서 확정)",
      "콜센터명": "제주콜센터",
      "콜센터번호": "TBD",
      "콜센터운영시간": "평일 09:00~18:00 (점심 12:00~13:00), 무인민원발급기 24시간"
    },
    {
      "emd_code": "SP-EMD-DAEJEONG",
      "team_code": "welfare",
      "도이름": "제주특별자치도",
      "시이름": "서귀포시",
      "읍면동이름": "대정읍",
      "팀이름": "주민복지팀",
      "입력_문구": "기초생활수급·기초연금 접수, 보훈 접수(1차 접수, 최종 심사는 시청 소관) 관련 접수·신청",
      "출력_문구": "복지 신청 접수증(지급결정은 시청 복지위생국에서 확정)",
      "콜센터명": "제주콜센터",
      "콜센터번호": "TBD",
      "콜센터운영시간": "평일 09:00~18:00 (점심 12:00~13:00), 무인민원발급기 24시간"
    },
    {
      "emd_code": "SP-EMD-DAEJEONG",
      "team_code": "outreach",
      "도이름": "제주특별자치도",
      "시이름": "서귀포시",
      "읍면동이름": "대정읍",
      "팀이름": "찾아가는복지팀",
      "입력_문구": "복지 사각지대 발굴, 방문 상담 관련 접수·신청",
      "출력_문구": "방문상담 결과, 복지서비스 연계",
      "콜센터명": "제주콜센터",
      "콜센터번호": "TBD",
      "콜센터운영시간": "평일 09:00~18:00 (점심 12:00~13:00), 무인민원발급기 24시간"
    },
    {
      "emd_code": "SP-EMD-NAMWON",
      "team_code": "general",
      "도이름": "제주특별자치도",
      "시이름": "서귀포시",
      "읍면동이름": "남원읍",
      "팀이름": "총무팀",
      "입력_문구": "민방위, 청소·환경정비, 이륜차 민원, 청사 관리 관련 접수·신청",
      "출력_문구": "민방위 훈련·청소환경정비 처리 결과, 청사 이용 안내",
      "콜센터명": "제주콜센터",
      "콜센터번호": "TBD",
      "콜센터운영시간": "평일 09:00~18:00 (점심 12:00~13:00), 무인민원발급기 24시간"
    },
    {
      "emd_code": "SP-EMD-NAMWON",
      "team_code": "civil",
      "도이름": "제주특별자치도",
      "시이름": "서귀포시",
      "읍면동이름": "남원읍",
      "팀이름": "민원팀",
      "입력_문구": "주민등록등초본, 가족관계등록, 인감증명 등 제증명 발급 관련 접수·신청",
      "출력_문구": "즉시발급 증명서(등초본·인감증명 등)",
      "콜센터명": "제주콜센터",
      "콜센터번호": "TBD",
      "콜센터운영시간": "평일 09:00~18:00 (점심 12:00~13:00), 무인민원발급기 24시간"
    },
    {
      "emd_code": "SP-EMD-NAMWON",
      "team_code": "industry",
      "도이름": "제주특별자치도",
      "시이름": "서귀포시",
      "읍면동이름": "남원읍",
      "팀이름": "산업팀",
      "입력_문구": "농업경영체 등록, 영농지원, 지역 주력산업 현장 지원 관련 접수·신청",
      "출력_문구": "접수증(최종 등록·지원 결정은 시청 소관 부서에서 확정)",
      "콜센터명": "제주콜센터",
      "콜센터번호": "TBD",
      "콜센터운영시간": "평일 09:00~18:00 (점심 12:00~13:00), 무인민원발급기 24시간"
    },
    {
      "emd_code": "SP-EMD-NAMWON",
      "team_code": "welfare",
      "도이름": "제주특별자치도",
      "시이름": "서귀포시",
      "읍면동이름": "남원읍",
      "팀이름": "주민복지팀",
      "입력_문구": "기초생활수급·기초연금 접수, 보훈 접수(1차 접수, 최종 심사는 시청 소관) 관련 접수·신청",
      "출력_문구": "복지 신청 접수증(지급결정은 시청 복지위생국에서 확정)",
      "콜센터명": "제주콜센터",
      "콜센터번호": "TBD",
      "콜센터운영시간": "평일 09:00~18:00 (점심 12:00~13:00), 무인민원발급기 24시간"
    },
    {
      "emd_code": "SP-EMD-NAMWON",
      "team_code": "outreach",
      "도이름": "제주특별자치도",
      "시이름": "서귀포시",
      "읍면동이름": "남원읍",
      "팀이름": "찾아가는복지팀",
      "입력_문구": "복지 사각지대 발굴, 방문 상담 관련 접수·신청",
      "출력_문구": "방문상담 결과, 복지서비스 연계",
      "콜센터명": "제주콜센터",
      "콜센터번호": "TBD",
      "콜센터운영시간": "평일 09:00~18:00 (점심 12:00~13:00), 무인민원발급기 24시간"
    },
    {
      "emd_code": "SP-EMD-SEONGSAN",
      "team_code": "general",
      "도이름": "제주특별자치도",
      "시이름": "서귀포시",
      "읍면동이름": "성산읍",
      "팀이름": "총무팀",
      "입력_문구": "민방위, 청소·환경정비, 이륜차 민원, 청사 관리 관련 접수·신청",
      "출력_문구": "민방위 훈련·청소환경정비 처리 결과, 청사 이용 안내",
      "콜센터명": "제주콜센터",
      "콜센터번호": "TBD",
      "콜센터운영시간": "평일 09:00~18:00 (점심 12:00~13:00), 무인민원발급기 24시간"
    },
    {
      "emd_code": "SP-EMD-SEONGSAN",
      "team_code": "civil",
      "도이름": "제주특별자치도",
      "시이름": "서귀포시",
      "읍면동이름": "성산읍",
      "팀이름": "민원팀",
      "입력_문구": "주민등록등초본, 가족관계등록, 인감증명 등 제증명 발급 관련 접수·신청",
      "출력_문구": "즉시발급 증명서(등초본·인감증명 등)",
      "콜센터명": "제주콜센터",
      "콜센터번호": "TBD",
      "콜센터운영시간": "평일 09:00~18:00 (점심 12:00~13:00), 무인민원발급기 24시간"
    },
    {
      "emd_code": "SP-EMD-SEONGSAN",
      "team_code": "industry",
      "도이름": "제주특별자치도",
      "시이름": "서귀포시",
      "읍면동이름": "성산읍",
      "팀이름": "산업팀",
      "입력_문구": "농업경영체 등록, 영농지원, 지역 주력산업 현장 지원 관련 접수·신청",
      "출력_문구": "접수증(최종 등록·지원 결정은 시청 소관 부서에서 확정)",
      "콜센터명": "제주콜센터",
      "콜센터번호": "TBD",
      "콜센터운영시간": "평일 09:00~18:00 (점심 12:00~13:00), 무인민원발급기 24시간"
    },
    {
      "emd_code": "SP-EMD-SEONGSAN",
      "team_code": "welfare",
      "도이름": "제주특별자치도",
      "시이름": "서귀포시",
      "읍면동이름": "성산읍",
      "팀이름": "주민복지팀",
      "입력_문구": "기초생활수급·기초연금 접수, 보훈 접수(1차 접수, 최종 심사는 시청 소관) 관련 접수·신청",
      "출력_문구": "복지 신청 접수증(지급결정은 시청 복지위생국에서 확정)",
      "콜센터명": "제주콜센터",
      "콜센터번호": "TBD",
      "콜센터운영시간": "평일 09:00~18:00 (점심 12:00~13:00), 무인민원발급기 24시간"
    },
    {
      "emd_code": "SP-EMD-SEONGSAN",
      "team_code": "outreach",
      "도이름": "제주특별자치도",
      "시이름": "서귀포시",
      "읍면동이름": "성산읍",
      "팀이름": "찾아가는복지팀",
      "입력_문구": "복지 사각지대 발굴, 방문 상담 관련 접수·신청",
      "출력_문구": "방문상담 결과, 복지서비스 연계",
      "콜센터명": "제주콜센터",
      "콜센터번호": "TBD",
      "콜센터운영시간": "평일 09:00~18:00 (점심 12:00~13:00), 무인민원발급기 24시간"
    },
    {
      "emd_code": "SP-EMD-ANDEOK",
      "team_code": "general",
      "도이름": "제주특별자치도",
      "시이름": "서귀포시",
      "읍면동이름": "안덕면",
      "팀이름": "총무팀",
      "입력_문구": "민방위, 청소·환경정비, 이륜차 민원, 청사 관리 관련 접수·신청",
      "출력_문구": "민방위 훈련·청소환경정비 처리 결과, 청사 이용 안내",
      "콜센터명": "제주콜센터",
      "콜센터번호": "TBD",
      "콜센터운영시간": "평일 09:00~18:00 (점심 12:00~13:00), 무인민원발급기 24시간"
    },
    {
      "emd_code": "SP-EMD-ANDEOK",
      "team_code": "civil",
      "도이름": "제주특별자치도",
      "시이름": "서귀포시",
      "읍면동이름": "안덕면",
      "팀이름": "민원팀",
      "입력_문구": "주민등록등초본, 가족관계등록, 인감증명 등 제증명 발급 관련 접수·신청",
      "출력_문구": "즉시발급 증명서(등초본·인감증명 등)",
      "콜센터명": "제주콜센터",
      "콜센터번호": "TBD",
      "콜센터운영시간": "평일 09:00~18:00 (점심 12:00~13:00), 무인민원발급기 24시간"
    },
    {
      "emd_code": "SP-EMD-ANDEOK",
      "team_code": "industry",
      "도이름": "제주특별자치도",
      "시이름": "서귀포시",
      "읍면동이름": "안덕면",
      "팀이름": "산업팀",
      "입력_문구": "농업경영체 등록, 영농지원, 지역 주력산업 현장 지원 관련 접수·신청",
      "출력_문구": "접수증(최종 등록·지원 결정은 시청 소관 부서에서 확정)",
      "콜센터명": "제주콜센터",
      "콜센터번호": "TBD",
      "콜센터운영시간": "평일 09:00~18:00 (점심 12:00~13:00), 무인민원발급기 24시간"
    },
    {
      "emd_code": "SP-EMD-ANDEOK",
      "team_code": "welfare",
      "도이름": "제주특별자치도",
      "시이름": "서귀포시",
      "읍면동이름": "안덕면",
      "팀이름": "주민복지팀",
      "입력_문구": "기초생활수급·기초연금 접수, 보훈 접수(1차 접수, 최종 심사는 시청 소관) 관련 접수·신청",
      "출력_문구": "복지 신청 접수증(지급결정은 시청 복지위생국에서 확정)",
      "콜센터명": "제주콜센터",
      "콜센터번호": "TBD",
      "콜센터운영시간": "평일 09:00~18:00 (점심 12:00~13:00), 무인민원발급기 24시간"
    },
    {
      "emd_code": "SP-EMD-ANDEOK",
      "team_code": "outreach",
      "도이름": "제주특별자치도",
      "시이름": "서귀포시",
      "읍면동이름": "안덕면",
      "팀이름": "찾아가는복지팀",
      "입력_문구": "복지 사각지대 발굴, 방문 상담 관련 접수·신청",
      "출력_문구": "방문상담 결과, 복지서비스 연계",
      "콜센터명": "제주콜센터",
      "콜센터번호": "TBD",
      "콜센터운영시간": "평일 09:00~18:00 (점심 12:00~13:00), 무인민원발급기 24시간"
    },
    {
      "emd_code": "SP-EMD-PYOSEON",
      "team_code": "general",
      "도이름": "제주특별자치도",
      "시이름": "서귀포시",
      "읍면동이름": "표선면",
      "팀이름": "총무팀",
      "입력_문구": "민방위, 청소·환경정비, 이륜차 민원, 청사 관리 관련 접수·신청",
      "출력_문구": "민방위 훈련·청소환경정비 처리 결과, 청사 이용 안내",
      "콜센터명": "제주콜센터",
      "콜센터번호": "TBD",
      "콜센터운영시간": "평일 09:00~18:00 (점심 12:00~13:00), 무인민원발급기 24시간"
    },
    {
      "emd_code": "SP-EMD-PYOSEON",
      "team_code": "civil",
      "도이름": "제주특별자치도",
      "시이름": "서귀포시",
      "읍면동이름": "표선면",
      "팀이름": "민원팀",
      "입력_문구": "주민등록등초본, 가족관계등록, 인감증명 등 제증명 발급 관련 접수·신청",
      "출력_문구": "즉시발급 증명서(등초본·인감증명 등)",
      "콜센터명": "제주콜센터",
      "콜센터번호": "TBD",
      "콜센터운영시간": "평일 09:00~18:00 (점심 12:00~13:00), 무인민원발급기 24시간"
    },
    {
      "emd_code": "SP-EMD-PYOSEON",
      "team_code": "industry",
      "도이름": "제주특별자치도",
      "시이름": "서귀포시",
      "읍면동이름": "표선면",
      "팀이름": "산업팀",
      "입력_문구": "농업경영체 등록, 영농지원, 지역 주력산업 현장 지원 관련 접수·신청",
      "출력_문구": "접수증(최종 등록·지원 결정은 시청 소관 부서에서 확정)",
      "콜센터명": "제주콜센터",
      "콜센터번호": "TBD",
      "콜센터운영시간": "평일 09:00~18:00 (점심 12:00~13:00), 무인민원발급기 24시간"
    },
    {
      "emd_code": "SP-EMD-PYOSEON",
      "team_code": "welfare",
      "도이름": "제주특별자치도",
      "시이름": "서귀포시",
      "읍면동이름": "표선면",
      "팀이름": "주민복지팀",
      "입력_문구": "기초생활수급·기초연금 접수, 보훈 접수(1차 접수, 최종 심사는 시청 소관) 관련 접수·신청",
      "출력_문구": "복지 신청 접수증(지급결정은 시청 복지위생국에서 확정)",
      "콜센터명": "제주콜센터",
      "콜센터번호": "TBD",
      "콜센터운영시간": "평일 09:00~18:00 (점심 12:00~13:00), 무인민원발급기 24시간"
    },
    {
      "emd_code": "SP-EMD-PYOSEON",
      "team_code": "outreach",
      "도이름": "제주특별자치도",
      "시이름": "서귀포시",
      "읍면동이름": "표선면",
      "팀이름": "찾아가는복지팀",
      "입력_문구": "복지 사각지대 발굴, 방문 상담 관련 접수·신청",
      "출력_문구": "방문상담 결과, 복지서비스 연계",
      "콜센터명": "제주콜센터",
      "콜센터번호": "TBD",
      "콜센터운영시간": "평일 09:00~18:00 (점심 12:00~13:00), 무인민원발급기 24시간"
    },
    {
      "emd_code": "SP-EMD-ILDO1",
      "team_code": "general",
      "도이름": "제주특별자치도",
      "시이름": "제주시",
      "읍면동이름": "일도1동",
      "팀이름": "총무팀",
      "입력_문구": "민방위, 청소·환경정비, 이륜차 민원, 청사 관리 관련 접수·신청",
      "출력_문구": "민방위 훈련·청소환경정비 처리 결과, 청사 이용 안내",
      "콜센터명": "제주콜센터",
      "콜센터번호": "TBD",
      "콜센터운영시간": "평일 09:00~18:00 (점심 12:00~13:00), 무인민원발급기 24시간"
    },
    {
      "emd_code": "SP-EMD-ILDO1",
      "team_code": "civil",
      "도이름": "제주특별자치도",
      "시이름": "제주시",
      "읍면동이름": "일도1동",
      "팀이름": "민원팀",
      "입력_문구": "주민등록등초본, 가족관계등록, 인감증명 등 제증명 발급 관련 접수·신청",
      "출력_문구": "즉시발급 증명서(등초본·인감증명 등)",
      "콜센터명": "제주콜센터",
      "콜센터번호": "TBD",
      "콜센터운영시간": "평일 09:00~18:00 (점심 12:00~13:00), 무인민원발급기 24시간"
    },
    {
      "emd_code": "SP-EMD-ILDO1",
      "team_code": "welfare",
      "도이름": "제주특별자치도",
      "시이름": "제주시",
      "읍면동이름": "일도1동",
      "팀이름": "주민복지팀",
      "입력_문구": "기초생활수급·기초연금 접수, 보훈 접수(1차 접수, 최종 심사는 시청 소관) 관련 접수·신청",
      "출력_문구": "복지 신청 접수증(지급결정은 시청 복지위생국에서 확정)",
      "콜센터명": "제주콜센터",
      "콜센터번호": "TBD",
      "콜센터운영시간": "평일 09:00~18:00 (점심 12:00~13:00), 무인민원발급기 24시간"
    },
    {
      "emd_code": "SP-EMD-ILDO1",
      "team_code": "outreach",
      "도이름": "제주특별자치도",
      "시이름": "제주시",
      "읍면동이름": "일도1동",
      "팀이름": "찾아가는복지팀",
      "입력_문구": "복지 사각지대 발굴, 방문 상담 관련 접수·신청",
      "출력_문구": "방문상담 결과, 복지서비스 연계",
      "콜센터명": "제주콜센터",
      "콜센터번호": "TBD",
      "콜센터운영시간": "평일 09:00~18:00 (점심 12:00~13:00), 무인민원발급기 24시간"
    },
    {
      "emd_code": "SP-EMD-ILDO2",
      "team_code": "general",
      "도이름": "제주특별자치도",
      "시이름": "제주시",
      "읍면동이름": "일도2동",
      "팀이름": "총무팀",
      "입력_문구": "민방위, 청소·환경정비, 이륜차 민원, 청사 관리 관련 접수·신청",
      "출력_문구": "민방위 훈련·청소환경정비 처리 결과, 청사 이용 안내",
      "콜센터명": "제주콜센터",
      "콜센터번호": "TBD",
      "콜센터운영시간": "평일 09:00~18:00 (점심 12:00~13:00), 무인민원발급기 24시간"
    },
    {
      "emd_code": "SP-EMD-ILDO2",
      "team_code": "civil",
      "도이름": "제주특별자치도",
      "시이름": "제주시",
      "읍면동이름": "일도2동",
      "팀이름": "민원팀",
      "입력_문구": "주민등록등초본, 가족관계등록, 인감증명 등 제증명 발급 관련 접수·신청",
      "출력_문구": "즉시발급 증명서(등초본·인감증명 등)",
      "콜센터명": "제주콜센터",
      "콜센터번호": "TBD",
      "콜센터운영시간": "평일 09:00~18:00 (점심 12:00~13:00), 무인민원발급기 24시간"
    },
    {
      "emd_code": "SP-EMD-ILDO2",
      "team_code": "welfare",
      "도이름": "제주특별자치도",
      "시이름": "제주시",
      "읍면동이름": "일도2동",
      "팀이름": "주민복지팀",
      "입력_문구": "기초생활수급·기초연금 접수, 보훈 접수(1차 접수, 최종 심사는 시청 소관) 관련 접수·신청",
      "출력_문구": "복지 신청 접수증(지급결정은 시청 복지위생국에서 확정)",
      "콜센터명": "제주콜센터",
      "콜센터번호": "TBD",
      "콜센터운영시간": "평일 09:00~18:00 (점심 12:00~13:00), 무인민원발급기 24시간"
    },
    {
      "emd_code": "SP-EMD-ILDO2",
      "team_code": "outreach",
      "도이름": "제주특별자치도",
      "시이름": "제주시",
      "읍면동이름": "일도2동",
      "팀이름": "찾아가는복지팀",
      "입력_문구": "복지 사각지대 발굴, 방문 상담 관련 접수·신청",
      "출력_문구": "방문상담 결과, 복지서비스 연계",
      "콜센터명": "제주콜센터",
      "콜센터번호": "TBD",
      "콜센터운영시간": "평일 09:00~18:00 (점심 12:00~13:00), 무인민원발급기 24시간"
    },
    {
      "emd_code": "SP-EMD-IDO1",
      "team_code": "general",
      "도이름": "제주특별자치도",
      "시이름": "제주시",
      "읍면동이름": "이도1동",
      "팀이름": "총무팀",
      "입력_문구": "민방위, 청소·환경정비, 이륜차 민원, 청사 관리 관련 접수·신청",
      "출력_문구": "민방위 훈련·청소환경정비 처리 결과, 청사 이용 안내",
      "콜센터명": "제주콜센터",
      "콜센터번호": "TBD",
      "콜센터운영시간": "평일 09:00~18:00 (점심 12:00~13:00), 무인민원발급기 24시간"
    },
    {
      "emd_code": "SP-EMD-IDO1",
      "team_code": "civil",
      "도이름": "제주특별자치도",
      "시이름": "제주시",
      "읍면동이름": "이도1동",
      "팀이름": "민원팀",
      "입력_문구": "주민등록등초본, 가족관계등록, 인감증명 등 제증명 발급 관련 접수·신청",
      "출력_문구": "즉시발급 증명서(등초본·인감증명 등)",
      "콜센터명": "제주콜센터",
      "콜센터번호": "TBD",
      "콜센터운영시간": "평일 09:00~18:00 (점심 12:00~13:00), 무인민원발급기 24시간"
    },
    {
      "emd_code": "SP-EMD-IDO1",
      "team_code": "welfare",
      "도이름": "제주특별자치도",
      "시이름": "제주시",
      "읍면동이름": "이도1동",
      "팀이름": "주민복지팀",
      "입력_문구": "기초생활수급·기초연금 접수, 보훈 접수(1차 접수, 최종 심사는 시청 소관) 관련 접수·신청",
      "출력_문구": "복지 신청 접수증(지급결정은 시청 복지위생국에서 확정)",
      "콜센터명": "제주콜센터",
      "콜센터번호": "TBD",
      "콜센터운영시간": "평일 09:00~18:00 (점심 12:00~13:00), 무인민원발급기 24시간"
    },
    {
      "emd_code": "SP-EMD-IDO1",
      "team_code": "outreach",
      "도이름": "제주특별자치도",
      "시이름": "제주시",
      "읍면동이름": "이도1동",
      "팀이름": "찾아가는복지팀",
      "입력_문구": "복지 사각지대 발굴, 방문 상담 관련 접수·신청",
      "출력_문구": "방문상담 결과, 복지서비스 연계",
      "콜센터명": "제주콜센터",
      "콜센터번호": "TBD",
      "콜센터운영시간": "평일 09:00~18:00 (점심 12:00~13:00), 무인민원발급기 24시간"
    },
    {
      "emd_code": "SP-EMD-IDO2",
      "team_code": "general",
      "도이름": "제주특별자치도",
      "시이름": "제주시",
      "읍면동이름": "이도2동",
      "팀이름": "총무팀",
      "입력_문구": "민방위, 청소·환경정비, 이륜차 민원, 청사 관리 관련 접수·신청",
      "출력_문구": "민방위 훈련·청소환경정비 처리 결과, 청사 이용 안내",
      "콜센터명": "제주콜센터",
      "콜센터번호": "TBD",
      "콜센터운영시간": "평일 09:00~18:00 (점심 12:00~13:00), 무인민원발급기 24시간"
    },
    {
      "emd_code": "SP-EMD-IDO2",
      "team_code": "civil",
      "도이름": "제주특별자치도",
      "시이름": "제주시",
      "읍면동이름": "이도2동",
      "팀이름": "민원팀",
      "입력_문구": "주민등록등초본, 가족관계등록, 인감증명 등 제증명 발급 관련 접수·신청",
      "출력_문구": "즉시발급 증명서(등초본·인감증명 등)",
      "콜센터명": "제주콜센터",
      "콜센터번호": "TBD",
      "콜센터운영시간": "평일 09:00~18:00 (점심 12:00~13:00), 무인민원발급기 24시간"
    },
    {
      "emd_code": "SP-EMD-IDO2",
      "team_code": "welfare",
      "도이름": "제주특별자치도",
      "시이름": "제주시",
      "읍면동이름": "이도2동",
      "팀이름": "주민복지팀",
      "입력_문구": "기초생활수급·기초연금 접수, 보훈 접수(1차 접수, 최종 심사는 시청 소관) 관련 접수·신청",
      "출력_문구": "복지 신청 접수증(지급결정은 시청 복지위생국에서 확정)",
      "콜센터명": "제주콜센터",
      "콜센터번호": "TBD",
      "콜센터운영시간": "평일 09:00~18:00 (점심 12:00~13:00), 무인민원발급기 24시간"
    },
    {
      "emd_code": "SP-EMD-IDO2",
      "team_code": "outreach",
      "도이름": "제주특별자치도",
      "시이름": "제주시",
      "읍면동이름": "이도2동",
      "팀이름": "찾아가는복지팀",
      "입력_문구": "복지 사각지대 발굴, 방문 상담 관련 접수·신청",
      "출력_문구": "방문상담 결과, 복지서비스 연계",
      "콜센터명": "제주콜센터",
      "콜센터번호": "TBD",
      "콜센터운영시간": "평일 09:00~18:00 (점심 12:00~13:00), 무인민원발급기 24시간"
    },
    {
      "emd_code": "SP-EMD-SAMDO1",
      "team_code": "general",
      "도이름": "제주특별자치도",
      "시이름": "제주시",
      "읍면동이름": "삼도1동",
      "팀이름": "총무팀",
      "입력_문구": "민방위, 청소·환경정비, 이륜차 민원, 청사 관리 관련 접수·신청",
      "출력_문구": "민방위 훈련·청소환경정비 처리 결과, 청사 이용 안내",
      "콜센터명": "제주콜센터",
      "콜센터번호": "TBD",
      "콜센터운영시간": "평일 09:00~18:00 (점심 12:00~13:00), 무인민원발급기 24시간"
    },
    {
      "emd_code": "SP-EMD-SAMDO1",
      "team_code": "civil",
      "도이름": "제주특별자치도",
      "시이름": "제주시",
      "읍면동이름": "삼도1동",
      "팀이름": "민원팀",
      "입력_문구": "주민등록등초본, 가족관계등록, 인감증명 등 제증명 발급 관련 접수·신청",
      "출력_문구": "즉시발급 증명서(등초본·인감증명 등)",
      "콜센터명": "제주콜센터",
      "콜센터번호": "TBD",
      "콜센터운영시간": "평일 09:00~18:00 (점심 12:00~13:00), 무인민원발급기 24시간"
    },
    {
      "emd_code": "SP-EMD-SAMDO1",
      "team_code": "welfare",
      "도이름": "제주특별자치도",
      "시이름": "제주시",
      "읍면동이름": "삼도1동",
      "팀이름": "주민복지팀",
      "입력_문구": "기초생활수급·기초연금 접수, 보훈 접수(1차 접수, 최종 심사는 시청 소관) 관련 접수·신청",
      "출력_문구": "복지 신청 접수증(지급결정은 시청 복지위생국에서 확정)",
      "콜센터명": "제주콜센터",
      "콜센터번호": "TBD",
      "콜센터운영시간": "평일 09:00~18:00 (점심 12:00~13:00), 무인민원발급기 24시간"
    },
    {
      "emd_code": "SP-EMD-SAMDO1",
      "team_code": "outreach",
      "도이름": "제주특별자치도",
      "시이름": "제주시",
      "읍면동이름": "삼도1동",
      "팀이름": "찾아가는복지팀",
      "입력_문구": "복지 사각지대 발굴, 방문 상담 관련 접수·신청",
      "출력_문구": "방문상담 결과, 복지서비스 연계",
      "콜센터명": "제주콜센터",
      "콜센터번호": "TBD",
      "콜센터운영시간": "평일 09:00~18:00 (점심 12:00~13:00), 무인민원발급기 24시간"
    },
    {
      "emd_code": "SP-EMD-SAMDO2",
      "team_code": "general",
      "도이름": "제주특별자치도",
      "시이름": "제주시",
      "읍면동이름": "삼도2동",
      "팀이름": "총무팀",
      "입력_문구": "민방위, 청소·환경정비, 이륜차 민원, 청사 관리 관련 접수·신청",
      "출력_문구": "민방위 훈련·청소환경정비 처리 결과, 청사 이용 안내",
      "콜센터명": "제주콜센터",
      "콜센터번호": "TBD",
      "콜센터운영시간": "평일 09:00~18:00 (점심 12:00~13:00), 무인민원발급기 24시간"
    },
    {
      "emd_code": "SP-EMD-SAMDO2",
      "team_code": "civil",
      "도이름": "제주특별자치도",
      "시이름": "제주시",
      "읍면동이름": "삼도2동",
      "팀이름": "민원팀",
      "입력_문구": "주민등록등초본, 가족관계등록, 인감증명 등 제증명 발급 관련 접수·신청",
      "출력_문구": "즉시발급 증명서(등초본·인감증명 등)",
      "콜센터명": "제주콜센터",
      "콜센터번호": "TBD",
      "콜센터운영시간": "평일 09:00~18:00 (점심 12:00~13:00), 무인민원발급기 24시간"
    },
    {
      "emd_code": "SP-EMD-SAMDO2",
      "team_code": "welfare",
      "도이름": "제주특별자치도",
      "시이름": "제주시",
      "읍면동이름": "삼도2동",
      "팀이름": "주민복지팀",
      "입력_문구": "기초생활수급·기초연금 접수, 보훈 접수(1차 접수, 최종 심사는 시청 소관) 관련 접수·신청",
      "출력_문구": "복지 신청 접수증(지급결정은 시청 복지위생국에서 확정)",
      "콜센터명": "제주콜센터",
      "콜센터번호": "TBD",
      "콜센터운영시간": "평일 09:00~18:00 (점심 12:00~13:00), 무인민원발급기 24시간"
    },
    {
      "emd_code": "SP-EMD-SAMDO2",
      "team_code": "outreach",
      "도이름": "제주특별자치도",
      "시이름": "제주시",
      "읍면동이름": "삼도2동",
      "팀이름": "찾아가는복지팀",
      "입력_문구": "복지 사각지대 발굴, 방문 상담 관련 접수·신청",
      "출력_문구": "방문상담 결과, 복지서비스 연계",
      "콜센터명": "제주콜센터",
      "콜센터번호": "TBD",
      "콜센터운영시간": "평일 09:00~18:00 (점심 12:00~13:00), 무인민원발급기 24시간"
    },
    {
      "emd_code": "SP-EMD-YONGDAM1",
      "team_code": "general",
      "도이름": "제주특별자치도",
      "시이름": "제주시",
      "읍면동이름": "용담1동",
      "팀이름": "총무팀",
      "입력_문구": "민방위, 청소·환경정비, 이륜차 민원, 청사 관리 관련 접수·신청",
      "출력_문구": "민방위 훈련·청소환경정비 처리 결과, 청사 이용 안내",
      "콜센터명": "제주콜센터",
      "콜센터번호": "TBD",
      "콜센터운영시간": "평일 09:00~18:00 (점심 12:00~13:00), 무인민원발급기 24시간"
    },
    {
      "emd_code": "SP-EMD-YONGDAM1",
      "team_code": "civil",
      "도이름": "제주특별자치도",
      "시이름": "제주시",
      "읍면동이름": "용담1동",
      "팀이름": "민원팀",
      "입력_문구": "주민등록등초본, 가족관계등록, 인감증명 등 제증명 발급 관련 접수·신청",
      "출력_문구": "즉시발급 증명서(등초본·인감증명 등)",
      "콜센터명": "제주콜센터",
      "콜센터번호": "TBD",
      "콜센터운영시간": "평일 09:00~18:00 (점심 12:00~13:00), 무인민원발급기 24시간"
    },
    {
      "emd_code": "SP-EMD-YONGDAM1",
      "team_code": "welfare",
      "도이름": "제주특별자치도",
      "시이름": "제주시",
      "읍면동이름": "용담1동",
      "팀이름": "주민복지팀",
      "입력_문구": "기초생활수급·기초연금 접수, 보훈 접수(1차 접수, 최종 심사는 시청 소관) 관련 접수·신청",
      "출력_문구": "복지 신청 접수증(지급결정은 시청 복지위생국에서 확정)",
      "콜센터명": "제주콜센터",
      "콜센터번호": "TBD",
      "콜센터운영시간": "평일 09:00~18:00 (점심 12:00~13:00), 무인민원발급기 24시간"
    },
    {
      "emd_code": "SP-EMD-YONGDAM1",
      "team_code": "outreach",
      "도이름": "제주특별자치도",
      "시이름": "제주시",
      "읍면동이름": "용담1동",
      "팀이름": "찾아가는복지팀",
      "입력_문구": "복지 사각지대 발굴, 방문 상담 관련 접수·신청",
      "출력_문구": "방문상담 결과, 복지서비스 연계",
      "콜센터명": "제주콜센터",
      "콜센터번호": "TBD",
      "콜센터운영시간": "평일 09:00~18:00 (점심 12:00~13:00), 무인민원발급기 24시간"
    },
    {
      "emd_code": "SP-EMD-YONGDAM2",
      "team_code": "general",
      "도이름": "제주특별자치도",
      "시이름": "제주시",
      "읍면동이름": "용담2동",
      "팀이름": "총무팀",
      "입력_문구": "민방위, 청소·환경정비, 이륜차 민원, 청사 관리 관련 접수·신청",
      "출력_문구": "민방위 훈련·청소환경정비 처리 결과, 청사 이용 안내",
      "콜센터명": "제주콜센터",
      "콜센터번호": "TBD",
      "콜센터운영시간": "평일 09:00~18:00 (점심 12:00~13:00), 무인민원발급기 24시간"
    },
    {
      "emd_code": "SP-EMD-YONGDAM2",
      "team_code": "civil",
      "도이름": "제주특별자치도",
      "시이름": "제주시",
      "읍면동이름": "용담2동",
      "팀이름": "민원팀",
      "입력_문구": "주민등록등초본, 가족관계등록, 인감증명 등 제증명 발급 관련 접수·신청",
      "출력_문구": "즉시발급 증명서(등초본·인감증명 등)",
      "콜센터명": "제주콜센터",
      "콜센터번호": "TBD",
      "콜센터운영시간": "평일 09:00~18:00 (점심 12:00~13:00), 무인민원발급기 24시간"
    },
    {
      "emd_code": "SP-EMD-YONGDAM2",
      "team_code": "welfare",
      "도이름": "제주특별자치도",
      "시이름": "제주시",
      "읍면동이름": "용담2동",
      "팀이름": "주민복지팀",
      "입력_문구": "기초생활수급·기초연금 접수, 보훈 접수(1차 접수, 최종 심사는 시청 소관) 관련 접수·신청",
      "출력_문구": "복지 신청 접수증(지급결정은 시청 복지위생국에서 확정)",
      "콜센터명": "제주콜센터",
      "콜센터번호": "TBD",
      "콜센터운영시간": "평일 09:00~18:00 (점심 12:00~13:00), 무인민원발급기 24시간"
    },
    {
      "emd_code": "SP-EMD-YONGDAM2",
      "team_code": "outreach",
      "도이름": "제주특별자치도",
      "시이름": "제주시",
      "읍면동이름": "용담2동",
      "팀이름": "찾아가는복지팀",
      "입력_문구": "복지 사각지대 발굴, 방문 상담 관련 접수·신청",
      "출력_문구": "방문상담 결과, 복지서비스 연계",
      "콜센터명": "제주콜센터",
      "콜센터번호": "TBD",
      "콜센터운영시간": "평일 09:00~18:00 (점심 12:00~13:00), 무인민원발급기 24시간"
    },
    {
      "emd_code": "SP-EMD-GEONIP",
      "team_code": "general",
      "도이름": "제주특별자치도",
      "시이름": "제주시",
      "읍면동이름": "건입동",
      "팀이름": "총무팀",
      "입력_문구": "민방위, 청소·환경정비, 이륜차 민원, 청사 관리 관련 접수·신청",
      "출력_문구": "민방위 훈련·청소환경정비 처리 결과, 청사 이용 안내",
      "콜센터명": "제주콜센터",
      "콜센터번호": "TBD",
      "콜센터운영시간": "평일 09:00~18:00 (점심 12:00~13:00), 무인민원발급기 24시간"
    },
    {
      "emd_code": "SP-EMD-GEONIP",
      "team_code": "civil",
      "도이름": "제주특별자치도",
      "시이름": "제주시",
      "읍면동이름": "건입동",
      "팀이름": "민원팀",
      "입력_문구": "주민등록등초본, 가족관계등록, 인감증명 등 제증명 발급 관련 접수·신청",
      "출력_문구": "즉시발급 증명서(등초본·인감증명 등)",
      "콜센터명": "제주콜센터",
      "콜센터번호": "TBD",
      "콜센터운영시간": "평일 09:00~18:00 (점심 12:00~13:00), 무인민원발급기 24시간"
    },
    {
      "emd_code": "SP-EMD-GEONIP",
      "team_code": "welfare",
      "도이름": "제주특별자치도",
      "시이름": "제주시",
      "읍면동이름": "건입동",
      "팀이름": "주민복지팀",
      "입력_문구": "기초생활수급·기초연금 접수, 보훈 접수(1차 접수, 최종 심사는 시청 소관) 관련 접수·신청",
      "출력_문구": "복지 신청 접수증(지급결정은 시청 복지위생국에서 확정)",
      "콜센터명": "제주콜센터",
      "콜센터번호": "TBD",
      "콜센터운영시간": "평일 09:00~18:00 (점심 12:00~13:00), 무인민원발급기 24시간"
    },
    {
      "emd_code": "SP-EMD-GEONIP",
      "team_code": "outreach",
      "도이름": "제주특별자치도",
      "시이름": "제주시",
      "읍면동이름": "건입동",
      "팀이름": "찾아가는복지팀",
      "입력_문구": "복지 사각지대 발굴, 방문 상담 관련 접수·신청",
      "출력_문구": "방문상담 결과, 복지서비스 연계",
      "콜센터명": "제주콜센터",
      "콜센터번호": "TBD",
      "콜센터운영시간": "평일 09:00~18:00 (점심 12:00~13:00), 무인민원발급기 24시간"
    },
    {
      "emd_code": "SP-EMD-HWABUK",
      "team_code": "general",
      "도이름": "제주특별자치도",
      "시이름": "제주시",
      "읍면동이름": "화북동",
      "팀이름": "총무팀",
      "입력_문구": "민방위, 청소·환경정비, 이륜차 민원, 청사 관리 관련 접수·신청",
      "출력_문구": "민방위 훈련·청소환경정비 처리 결과, 청사 이용 안내",
      "콜센터명": "제주콜센터",
      "콜센터번호": "TBD",
      "콜센터운영시간": "평일 09:00~18:00 (점심 12:00~13:00), 무인민원발급기 24시간"
    },
    {
      "emd_code": "SP-EMD-HWABUK",
      "team_code": "civil",
      "도이름": "제주특별자치도",
      "시이름": "제주시",
      "읍면동이름": "화북동",
      "팀이름": "민원팀",
      "입력_문구": "주민등록등초본, 가족관계등록, 인감증명 등 제증명 발급 관련 접수·신청",
      "출력_문구": "즉시발급 증명서(등초본·인감증명 등)",
      "콜센터명": "제주콜센터",
      "콜센터번호": "TBD",
      "콜센터운영시간": "평일 09:00~18:00 (점심 12:00~13:00), 무인민원발급기 24시간"
    },
    {
      "emd_code": "SP-EMD-HWABUK",
      "team_code": "welfare",
      "도이름": "제주특별자치도",
      "시이름": "제주시",
      "읍면동이름": "화북동",
      "팀이름": "주민복지팀",
      "입력_문구": "기초생활수급·기초연금 접수, 보훈 접수(1차 접수, 최종 심사는 시청 소관) 관련 접수·신청",
      "출력_문구": "복지 신청 접수증(지급결정은 시청 복지위생국에서 확정)",
      "콜센터명": "제주콜센터",
      "콜센터번호": "TBD",
      "콜센터운영시간": "평일 09:00~18:00 (점심 12:00~13:00), 무인민원발급기 24시간"
    },
    {
      "emd_code": "SP-EMD-HWABUK",
      "team_code": "outreach",
      "도이름": "제주특별자치도",
      "시이름": "제주시",
      "읍면동이름": "화북동",
      "팀이름": "찾아가는복지팀",
      "입력_문구": "복지 사각지대 발굴, 방문 상담 관련 접수·신청",
      "출력_문구": "방문상담 결과, 복지서비스 연계",
      "콜센터명": "제주콜센터",
      "콜센터번호": "TBD",
      "콜센터운영시간": "평일 09:00~18:00 (점심 12:00~13:00), 무인민원발급기 24시간"
    },
    {
      "emd_code": "SP-EMD-SAMYANG",
      "team_code": "general",
      "도이름": "제주특별자치도",
      "시이름": "제주시",
      "읍면동이름": "삼양동",
      "팀이름": "총무팀",
      "입력_문구": "민방위, 청소·환경정비, 이륜차 민원, 청사 관리 관련 접수·신청",
      "출력_문구": "민방위 훈련·청소환경정비 처리 결과, 청사 이용 안내",
      "콜센터명": "제주콜센터",
      "콜센터번호": "TBD",
      "콜센터운영시간": "평일 09:00~18:00 (점심 12:00~13:00), 무인민원발급기 24시간"
    },
    {
      "emd_code": "SP-EMD-SAMYANG",
      "team_code": "civil",
      "도이름": "제주특별자치도",
      "시이름": "제주시",
      "읍면동이름": "삼양동",
      "팀이름": "민원팀",
      "입력_문구": "주민등록등초본, 가족관계등록, 인감증명 등 제증명 발급 관련 접수·신청",
      "출력_문구": "즉시발급 증명서(등초본·인감증명 등)",
      "콜센터명": "제주콜센터",
      "콜센터번호": "TBD",
      "콜센터운영시간": "평일 09:00~18:00 (점심 12:00~13:00), 무인민원발급기 24시간"
    },
    {
      "emd_code": "SP-EMD-SAMYANG",
      "team_code": "welfare",
      "도이름": "제주특별자치도",
      "시이름": "제주시",
      "읍면동이름": "삼양동",
      "팀이름": "주민복지팀",
      "입력_문구": "기초생활수급·기초연금 접수, 보훈 접수(1차 접수, 최종 심사는 시청 소관) 관련 접수·신청",
      "출력_문구": "복지 신청 접수증(지급결정은 시청 복지위생국에서 확정)",
      "콜센터명": "제주콜센터",
      "콜센터번호": "TBD",
      "콜센터운영시간": "평일 09:00~18:00 (점심 12:00~13:00), 무인민원발급기 24시간"
    },
    {
      "emd_code": "SP-EMD-SAMYANG",
      "team_code": "outreach",
      "도이름": "제주특별자치도",
      "시이름": "제주시",
      "읍면동이름": "삼양동",
      "팀이름": "찾아가는복지팀",
      "입력_문구": "복지 사각지대 발굴, 방문 상담 관련 접수·신청",
      "출력_문구": "방문상담 결과, 복지서비스 연계",
      "콜센터명": "제주콜센터",
      "콜센터번호": "TBD",
      "콜센터운영시간": "평일 09:00~18:00 (점심 12:00~13:00), 무인민원발급기 24시간"
    },
    {
      "emd_code": "SP-EMD-BONGGAE",
      "team_code": "general",
      "도이름": "제주특별자치도",
      "시이름": "제주시",
      "읍면동이름": "봉개동",
      "팀이름": "총무팀",
      "입력_문구": "민방위, 청소·환경정비, 이륜차 민원, 청사 관리 관련 접수·신청",
      "출력_문구": "민방위 훈련·청소환경정비 처리 결과, 청사 이용 안내",
      "콜센터명": "제주콜센터",
      "콜센터번호": "TBD",
      "콜센터운영시간": "평일 09:00~18:00 (점심 12:00~13:00), 무인민원발급기 24시간"
    },
    {
      "emd_code": "SP-EMD-BONGGAE",
      "team_code": "civil",
      "도이름": "제주특별자치도",
      "시이름": "제주시",
      "읍면동이름": "봉개동",
      "팀이름": "민원팀",
      "입력_문구": "주민등록등초본, 가족관계등록, 인감증명 등 제증명 발급 관련 접수·신청",
      "출력_문구": "즉시발급 증명서(등초본·인감증명 등)",
      "콜센터명": "제주콜센터",
      "콜센터번호": "TBD",
      "콜센터운영시간": "평일 09:00~18:00 (점심 12:00~13:00), 무인민원발급기 24시간"
    },
    {
      "emd_code": "SP-EMD-BONGGAE",
      "team_code": "welfare",
      "도이름": "제주특별자치도",
      "시이름": "제주시",
      "읍면동이름": "봉개동",
      "팀이름": "주민복지팀",
      "입력_문구": "기초생활수급·기초연금 접수, 보훈 접수(1차 접수, 최종 심사는 시청 소관) 관련 접수·신청",
      "출력_문구": "복지 신청 접수증(지급결정은 시청 복지위생국에서 확정)",
      "콜센터명": "제주콜센터",
      "콜센터번호": "TBD",
      "콜센터운영시간": "평일 09:00~18:00 (점심 12:00~13:00), 무인민원발급기 24시간"
    },
    {
      "emd_code": "SP-EMD-BONGGAE",
      "team_code": "outreach",
      "도이름": "제주특별자치도",
      "시이름": "제주시",
      "읍면동이름": "봉개동",
      "팀이름": "찾아가는복지팀",
      "입력_문구": "복지 사각지대 발굴, 방문 상담 관련 접수·신청",
      "출력_문구": "방문상담 결과, 복지서비스 연계",
      "콜센터명": "제주콜센터",
      "콜센터번호": "TBD",
      "콜센터운영시간": "평일 09:00~18:00 (점심 12:00~13:00), 무인민원발급기 24시간"
    },
    {
      "emd_code": "SP-EMD-ARA",
      "team_code": "general",
      "도이름": "제주특별자치도",
      "시이름": "제주시",
      "읍면동이름": "아라동",
      "팀이름": "총무팀",
      "입력_문구": "민방위, 청소·환경정비, 이륜차 민원, 청사 관리 관련 접수·신청",
      "출력_문구": "민방위 훈련·청소환경정비 처리 결과, 청사 이용 안내",
      "콜센터명": "제주콜센터",
      "콜센터번호": "TBD",
      "콜센터운영시간": "평일 09:00~18:00 (점심 12:00~13:00), 무인민원발급기 24시간"
    },
    {
      "emd_code": "SP-EMD-ARA",
      "team_code": "civil",
      "도이름": "제주특별자치도",
      "시이름": "제주시",
      "읍면동이름": "아라동",
      "팀이름": "민원팀",
      "입력_문구": "주민등록등초본, 가족관계등록, 인감증명 등 제증명 발급 관련 접수·신청",
      "출력_문구": "즉시발급 증명서(등초본·인감증명 등)",
      "콜센터명": "제주콜센터",
      "콜센터번호": "TBD",
      "콜센터운영시간": "평일 09:00~18:00 (점심 12:00~13:00), 무인민원발급기 24시간"
    },
    {
      "emd_code": "SP-EMD-ARA",
      "team_code": "welfare",
      "도이름": "제주특별자치도",
      "시이름": "제주시",
      "읍면동이름": "아라동",
      "팀이름": "주민복지팀",
      "입력_문구": "기초생활수급·기초연금 접수, 보훈 접수(1차 접수, 최종 심사는 시청 소관) 관련 접수·신청",
      "출력_문구": "복지 신청 접수증(지급결정은 시청 복지위생국에서 확정)",
      "콜센터명": "제주콜센터",
      "콜센터번호": "TBD",
      "콜센터운영시간": "평일 09:00~18:00 (점심 12:00~13:00), 무인민원발급기 24시간"
    },
    {
      "emd_code": "SP-EMD-ARA",
      "team_code": "outreach",
      "도이름": "제주특별자치도",
      "시이름": "제주시",
      "읍면동이름": "아라동",
      "팀이름": "찾아가는복지팀",
      "입력_문구": "복지 사각지대 발굴, 방문 상담 관련 접수·신청",
      "출력_문구": "방문상담 결과, 복지서비스 연계",
      "콜센터명": "제주콜센터",
      "콜센터번호": "TBD",
      "콜센터운영시간": "평일 09:00~18:00 (점심 12:00~13:00), 무인민원발급기 24시간"
    },
    {
      "emd_code": "SP-EMD-ORA",
      "team_code": "general",
      "도이름": "제주특별자치도",
      "시이름": "제주시",
      "읍면동이름": "오라동",
      "팀이름": "총무팀",
      "입력_문구": "민방위, 청소·환경정비, 이륜차 민원, 청사 관리 관련 접수·신청",
      "출력_문구": "민방위 훈련·청소환경정비 처리 결과, 청사 이용 안내",
      "콜센터명": "제주콜센터",
      "콜센터번호": "TBD",
      "콜센터운영시간": "평일 09:00~18:00 (점심 12:00~13:00), 무인민원발급기 24시간"
    },
    {
      "emd_code": "SP-EMD-ORA",
      "team_code": "civil",
      "도이름": "제주특별자치도",
      "시이름": "제주시",
      "읍면동이름": "오라동",
      "팀이름": "민원팀",
      "입력_문구": "주민등록등초본, 가족관계등록, 인감증명 등 제증명 발급 관련 접수·신청",
      "출력_문구": "즉시발급 증명서(등초본·인감증명 등)",
      "콜센터명": "제주콜센터",
      "콜센터번호": "TBD",
      "콜센터운영시간": "평일 09:00~18:00 (점심 12:00~13:00), 무인민원발급기 24시간"
    },
    {
      "emd_code": "SP-EMD-ORA",
      "team_code": "welfare",
      "도이름": "제주특별자치도",
      "시이름": "제주시",
      "읍면동이름": "오라동",
      "팀이름": "주민복지팀",
      "입력_문구": "기초생활수급·기초연금 접수, 보훈 접수(1차 접수, 최종 심사는 시청 소관) 관련 접수·신청",
      "출력_문구": "복지 신청 접수증(지급결정은 시청 복지위생국에서 확정)",
      "콜센터명": "제주콜센터",
      "콜센터번호": "TBD",
      "콜센터운영시간": "평일 09:00~18:00 (점심 12:00~13:00), 무인민원발급기 24시간"
    },
    {
      "emd_code": "SP-EMD-ORA",
      "team_code": "outreach",
      "도이름": "제주특별자치도",
      "시이름": "제주시",
      "읍면동이름": "오라동",
      "팀이름": "찾아가는복지팀",
      "입력_문구": "복지 사각지대 발굴, 방문 상담 관련 접수·신청",
      "출력_문구": "방문상담 결과, 복지서비스 연계",
      "콜센터명": "제주콜센터",
      "콜센터번호": "TBD",
      "콜센터운영시간": "평일 09:00~18:00 (점심 12:00~13:00), 무인민원발급기 24시간"
    },
    {
      "emd_code": "SP-EMD-YEONDONG",
      "team_code": "general",
      "도이름": "제주특별자치도",
      "시이름": "제주시",
      "읍면동이름": "연동",
      "팀이름": "총무팀",
      "입력_문구": "민방위, 청소·환경정비, 이륜차 민원, 청사 관리 관련 접수·신청",
      "출력_문구": "민방위 훈련·청소환경정비 처리 결과, 청사 이용 안내",
      "콜센터명": "제주콜센터",
      "콜센터번호": "TBD",
      "콜센터운영시간": "평일 09:00~18:00 (점심 12:00~13:00), 무인민원발급기 24시간"
    },
    {
      "emd_code": "SP-EMD-YEONDONG",
      "team_code": "civil",
      "도이름": "제주특별자치도",
      "시이름": "제주시",
      "읍면동이름": "연동",
      "팀이름": "민원팀",
      "입력_문구": "주민등록등초본, 가족관계등록, 인감증명 등 제증명 발급 관련 접수·신청",
      "출력_문구": "즉시발급 증명서(등초본·인감증명 등)",
      "콜센터명": "제주콜센터",
      "콜센터번호": "TBD",
      "콜센터운영시간": "평일 09:00~18:00 (점심 12:00~13:00), 무인민원발급기 24시간"
    },
    {
      "emd_code": "SP-EMD-YEONDONG",
      "team_code": "welfare",
      "도이름": "제주특별자치도",
      "시이름": "제주시",
      "읍면동이름": "연동",
      "팀이름": "주민복지팀",
      "입력_문구": "기초생활수급·기초연금 접수, 보훈 접수(1차 접수, 최종 심사는 시청 소관) 관련 접수·신청",
      "출력_문구": "복지 신청 접수증(지급결정은 시청 복지위생국에서 확정)",
      "콜센터명": "제주콜센터",
      "콜센터번호": "TBD",
      "콜센터운영시간": "평일 09:00~18:00 (점심 12:00~13:00), 무인민원발급기 24시간"
    },
    {
      "emd_code": "SP-EMD-YEONDONG",
      "team_code": "outreach",
      "도이름": "제주특별자치도",
      "시이름": "제주시",
      "읍면동이름": "연동",
      "팀이름": "찾아가는복지팀",
      "입력_문구": "복지 사각지대 발굴, 방문 상담 관련 접수·신청",
      "출력_문구": "방문상담 결과, 복지서비스 연계",
      "콜센터명": "제주콜센터",
      "콜센터번호": "TBD",
      "콜센터운영시간": "평일 09:00~18:00 (점심 12:00~13:00), 무인민원발급기 24시간"
    },
    {
      "emd_code": "SP-EMD-NOHYEONG",
      "team_code": "general",
      "도이름": "제주특별자치도",
      "시이름": "제주시",
      "읍면동이름": "노형동",
      "팀이름": "총무팀",
      "입력_문구": "민방위, 청소·환경정비, 이륜차 민원, 청사 관리 관련 접수·신청",
      "출력_문구": "민방위 훈련·청소환경정비 처리 결과, 청사 이용 안내",
      "콜센터명": "제주콜센터",
      "콜센터번호": "TBD",
      "콜센터운영시간": "평일 09:00~18:00 (점심 12:00~13:00), 무인민원발급기 24시간"
    },
    {
      "emd_code": "SP-EMD-NOHYEONG",
      "team_code": "civil",
      "도이름": "제주특별자치도",
      "시이름": "제주시",
      "읍면동이름": "노형동",
      "팀이름": "민원팀",
      "입력_문구": "주민등록등초본, 가족관계등록, 인감증명 등 제증명 발급 관련 접수·신청",
      "출력_문구": "즉시발급 증명서(등초본·인감증명 등)",
      "콜센터명": "제주콜센터",
      "콜센터번호": "TBD",
      "콜센터운영시간": "평일 09:00~18:00 (점심 12:00~13:00), 무인민원발급기 24시간"
    },
    {
      "emd_code": "SP-EMD-NOHYEONG",
      "team_code": "welfare",
      "도이름": "제주특별자치도",
      "시이름": "제주시",
      "읍면동이름": "노형동",
      "팀이름": "주민복지팀",
      "입력_문구": "기초생활수급·기초연금 접수, 보훈 접수(1차 접수, 최종 심사는 시청 소관) 관련 접수·신청",
      "출력_문구": "복지 신청 접수증(지급결정은 시청 복지위생국에서 확정)",
      "콜센터명": "제주콜센터",
      "콜센터번호": "TBD",
      "콜센터운영시간": "평일 09:00~18:00 (점심 12:00~13:00), 무인민원발급기 24시간"
    },
    {
      "emd_code": "SP-EMD-NOHYEONG",
      "team_code": "outreach",
      "도이름": "제주특별자치도",
      "시이름": "제주시",
      "읍면동이름": "노형동",
      "팀이름": "찾아가는복지팀",
      "입력_문구": "복지 사각지대 발굴, 방문 상담 관련 접수·신청",
      "출력_문구": "방문상담 결과, 복지서비스 연계",
      "콜센터명": "제주콜센터",
      "콜센터번호": "TBD",
      "콜센터운영시간": "평일 09:00~18:00 (점심 12:00~13:00), 무인민원발급기 24시간"
    },
    {
      "emd_code": "SP-EMD-OEDO",
      "team_code": "general",
      "도이름": "제주특별자치도",
      "시이름": "제주시",
      "읍면동이름": "외도동",
      "팀이름": "총무팀",
      "입력_문구": "민방위, 청소·환경정비, 이륜차 민원, 청사 관리 관련 접수·신청",
      "출력_문구": "민방위 훈련·청소환경정비 처리 결과, 청사 이용 안내",
      "콜센터명": "제주콜센터",
      "콜센터번호": "TBD",
      "콜센터운영시간": "평일 09:00~18:00 (점심 12:00~13:00), 무인민원발급기 24시간"
    },
    {
      "emd_code": "SP-EMD-OEDO",
      "team_code": "civil",
      "도이름": "제주특별자치도",
      "시이름": "제주시",
      "읍면동이름": "외도동",
      "팀이름": "민원팀",
      "입력_문구": "주민등록등초본, 가족관계등록, 인감증명 등 제증명 발급 관련 접수·신청",
      "출력_문구": "즉시발급 증명서(등초본·인감증명 등)",
      "콜센터명": "제주콜센터",
      "콜센터번호": "TBD",
      "콜센터운영시간": "평일 09:00~18:00 (점심 12:00~13:00), 무인민원발급기 24시간"
    },
    {
      "emd_code": "SP-EMD-OEDO",
      "team_code": "welfare",
      "도이름": "제주특별자치도",
      "시이름": "제주시",
      "읍면동이름": "외도동",
      "팀이름": "주민복지팀",
      "입력_문구": "기초생활수급·기초연금 접수, 보훈 접수(1차 접수, 최종 심사는 시청 소관) 관련 접수·신청",
      "출력_문구": "복지 신청 접수증(지급결정은 시청 복지위생국에서 확정)",
      "콜센터명": "제주콜센터",
      "콜센터번호": "TBD",
      "콜센터운영시간": "평일 09:00~18:00 (점심 12:00~13:00), 무인민원발급기 24시간"
    },
    {
      "emd_code": "SP-EMD-OEDO",
      "team_code": "outreach",
      "도이름": "제주특별자치도",
      "시이름": "제주시",
      "읍면동이름": "외도동",
      "팀이름": "찾아가는복지팀",
      "입력_문구": "복지 사각지대 발굴, 방문 상담 관련 접수·신청",
      "출력_문구": "방문상담 결과, 복지서비스 연계",
      "콜센터명": "제주콜센터",
      "콜센터번호": "TBD",
      "콜센터운영시간": "평일 09:00~18:00 (점심 12:00~13:00), 무인민원발급기 24시간"
    },
    {
      "emd_code": "SP-EMD-IHO",
      "team_code": "general",
      "도이름": "제주특별자치도",
      "시이름": "제주시",
      "읍면동이름": "이호동",
      "팀이름": "총무팀",
      "입력_문구": "민방위, 청소·환경정비, 이륜차 민원, 청사 관리 관련 접수·신청",
      "출력_문구": "민방위 훈련·청소환경정비 처리 결과, 청사 이용 안내",
      "콜센터명": "제주콜센터",
      "콜센터번호": "TBD",
      "콜센터운영시간": "평일 09:00~18:00 (점심 12:00~13:00), 무인민원발급기 24시간"
    },
    {
      "emd_code": "SP-EMD-IHO",
      "team_code": "civil",
      "도이름": "제주특별자치도",
      "시이름": "제주시",
      "읍면동이름": "이호동",
      "팀이름": "민원팀",
      "입력_문구": "주민등록등초본, 가족관계등록, 인감증명 등 제증명 발급 관련 접수·신청",
      "출력_문구": "즉시발급 증명서(등초본·인감증명 등)",
      "콜센터명": "제주콜센터",
      "콜센터번호": "TBD",
      "콜센터운영시간": "평일 09:00~18:00 (점심 12:00~13:00), 무인민원발급기 24시간"
    },
    {
      "emd_code": "SP-EMD-IHO",
      "team_code": "welfare",
      "도이름": "제주특별자치도",
      "시이름": "제주시",
      "읍면동이름": "이호동",
      "팀이름": "주민복지팀",
      "입력_문구": "기초생활수급·기초연금 접수, 보훈 접수(1차 접수, 최종 심사는 시청 소관) 관련 접수·신청",
      "출력_문구": "복지 신청 접수증(지급결정은 시청 복지위생국에서 확정)",
      "콜센터명": "제주콜센터",
      "콜센터번호": "TBD",
      "콜센터운영시간": "평일 09:00~18:00 (점심 12:00~13:00), 무인민원발급기 24시간"
    },
    {
      "emd_code": "SP-EMD-IHO",
      "team_code": "outreach",
      "도이름": "제주특별자치도",
      "시이름": "제주시",
      "읍면동이름": "이호동",
      "팀이름": "찾아가는복지팀",
      "입력_문구": "복지 사각지대 발굴, 방문 상담 관련 접수·신청",
      "출력_문구": "방문상담 결과, 복지서비스 연계",
      "콜센터명": "제주콜센터",
      "콜센터번호": "TBD",
      "콜센터운영시간": "평일 09:00~18:00 (점심 12:00~13:00), 무인민원발급기 24시간"
    },
    {
      "emd_code": "SP-EMD-DODU",
      "team_code": "general",
      "도이름": "제주특별자치도",
      "시이름": "제주시",
      "읍면동이름": "도두동",
      "팀이름": "총무팀",
      "입력_문구": "민방위, 청소·환경정비, 이륜차 민원, 청사 관리 관련 접수·신청",
      "출력_문구": "민방위 훈련·청소환경정비 처리 결과, 청사 이용 안내",
      "콜센터명": "제주콜센터",
      "콜센터번호": "TBD",
      "콜센터운영시간": "평일 09:00~18:00 (점심 12:00~13:00), 무인민원발급기 24시간"
    },
    {
      "emd_code": "SP-EMD-DODU",
      "team_code": "civil",
      "도이름": "제주특별자치도",
      "시이름": "제주시",
      "읍면동이름": "도두동",
      "팀이름": "민원팀",
      "입력_문구": "주민등록등초본, 가족관계등록, 인감증명 등 제증명 발급 관련 접수·신청",
      "출력_문구": "즉시발급 증명서(등초본·인감증명 등)",
      "콜센터명": "제주콜센터",
      "콜센터번호": "TBD",
      "콜센터운영시간": "평일 09:00~18:00 (점심 12:00~13:00), 무인민원발급기 24시간"
    },
    {
      "emd_code": "SP-EMD-DODU",
      "team_code": "welfare",
      "도이름": "제주특별자치도",
      "시이름": "제주시",
      "읍면동이름": "도두동",
      "팀이름": "주민복지팀",
      "입력_문구": "기초생활수급·기초연금 접수, 보훈 접수(1차 접수, 최종 심사는 시청 소관) 관련 접수·신청",
      "출력_문구": "복지 신청 접수증(지급결정은 시청 복지위생국에서 확정)",
      "콜센터명": "제주콜센터",
      "콜센터번호": "TBD",
      "콜센터운영시간": "평일 09:00~18:00 (점심 12:00~13:00), 무인민원발급기 24시간"
    },
    {
      "emd_code": "SP-EMD-DODU",
      "team_code": "outreach",
      "도이름": "제주특별자치도",
      "시이름": "제주시",
      "읍면동이름": "도두동",
      "팀이름": "찾아가는복지팀",
      "입력_문구": "복지 사각지대 발굴, 방문 상담 관련 접수·신청",
      "출력_문구": "방문상담 결과, 복지서비스 연계",
      "콜센터명": "제주콜센터",
      "콜센터번호": "TBD",
      "콜센터운영시간": "평일 09:00~18:00 (점심 12:00~13:00), 무인민원발급기 24시간"
    },
    {
      "emd_code": "SP-EMD-SONGSAN",
      "team_code": "general",
      "도이름": "제주특별자치도",
      "시이름": "서귀포시",
      "읍면동이름": "송산동",
      "팀이름": "총무팀",
      "입력_문구": "민방위, 청소·환경정비, 이륜차 민원, 청사 관리 관련 접수·신청",
      "출력_문구": "민방위 훈련·청소환경정비 처리 결과, 청사 이용 안내",
      "콜센터명": "제주콜센터",
      "콜센터번호": "TBD",
      "콜센터운영시간": "평일 09:00~18:00 (점심 12:00~13:00), 무인민원발급기 24시간"
    },
    {
      "emd_code": "SP-EMD-SONGSAN",
      "team_code": "civil",
      "도이름": "제주특별자치도",
      "시이름": "서귀포시",
      "읍면동이름": "송산동",
      "팀이름": "민원팀",
      "입력_문구": "주민등록등초본, 가족관계등록, 인감증명 등 제증명 발급 관련 접수·신청",
      "출력_문구": "즉시발급 증명서(등초본·인감증명 등)",
      "콜센터명": "제주콜센터",
      "콜센터번호": "TBD",
      "콜센터운영시간": "평일 09:00~18:00 (점심 12:00~13:00), 무인민원발급기 24시간"
    },
    {
      "emd_code": "SP-EMD-SONGSAN",
      "team_code": "welfare",
      "도이름": "제주특별자치도",
      "시이름": "서귀포시",
      "읍면동이름": "송산동",
      "팀이름": "주민복지팀",
      "입력_문구": "기초생활수급·기초연금 접수, 보훈 접수(1차 접수, 최종 심사는 시청 소관) 관련 접수·신청",
      "출력_문구": "복지 신청 접수증(지급결정은 시청 복지위생국에서 확정)",
      "콜센터명": "제주콜센터",
      "콜센터번호": "TBD",
      "콜센터운영시간": "평일 09:00~18:00 (점심 12:00~13:00), 무인민원발급기 24시간"
    },
    {
      "emd_code": "SP-EMD-SONGSAN",
      "team_code": "outreach",
      "도이름": "제주특별자치도",
      "시이름": "서귀포시",
      "읍면동이름": "송산동",
      "팀이름": "찾아가는복지팀",
      "입력_문구": "복지 사각지대 발굴, 방문 상담 관련 접수·신청",
      "출력_문구": "방문상담 결과, 복지서비스 연계",
      "콜센터명": "제주콜센터",
      "콜센터번호": "TBD",
      "콜센터운영시간": "평일 09:00~18:00 (점심 12:00~13:00), 무인민원발급기 24시간"
    },
    {
      "emd_code": "SP-EMD-JEONGBANG",
      "team_code": "general",
      "도이름": "제주특별자치도",
      "시이름": "서귀포시",
      "읍면동이름": "정방동",
      "팀이름": "총무팀",
      "입력_문구": "민방위, 청소·환경정비, 이륜차 민원, 청사 관리 관련 접수·신청",
      "출력_문구": "민방위 훈련·청소환경정비 처리 결과, 청사 이용 안내",
      "콜센터명": "제주콜센터",
      "콜센터번호": "TBD",
      "콜센터운영시간": "평일 09:00~18:00 (점심 12:00~13:00), 무인민원발급기 24시간"
    },
    {
      "emd_code": "SP-EMD-JEONGBANG",
      "team_code": "civil",
      "도이름": "제주특별자치도",
      "시이름": "서귀포시",
      "읍면동이름": "정방동",
      "팀이름": "민원팀",
      "입력_문구": "주민등록등초본, 가족관계등록, 인감증명 등 제증명 발급 관련 접수·신청",
      "출력_문구": "즉시발급 증명서(등초본·인감증명 등)",
      "콜센터명": "제주콜센터",
      "콜센터번호": "TBD",
      "콜센터운영시간": "평일 09:00~18:00 (점심 12:00~13:00), 무인민원발급기 24시간"
    },
    {
      "emd_code": "SP-EMD-JEONGBANG",
      "team_code": "welfare",
      "도이름": "제주특별자치도",
      "시이름": "서귀포시",
      "읍면동이름": "정방동",
      "팀이름": "주민복지팀",
      "입력_문구": "기초생활수급·기초연금 접수, 보훈 접수(1차 접수, 최종 심사는 시청 소관) 관련 접수·신청",
      "출력_문구": "복지 신청 접수증(지급결정은 시청 복지위생국에서 확정)",
      "콜센터명": "제주콜센터",
      "콜센터번호": "TBD",
      "콜센터운영시간": "평일 09:00~18:00 (점심 12:00~13:00), 무인민원발급기 24시간"
    },
    {
      "emd_code": "SP-EMD-JEONGBANG",
      "team_code": "outreach",
      "도이름": "제주특별자치도",
      "시이름": "서귀포시",
      "읍면동이름": "정방동",
      "팀이름": "찾아가는복지팀",
      "입력_문구": "복지 사각지대 발굴, 방문 상담 관련 접수·신청",
      "출력_문구": "방문상담 결과, 복지서비스 연계",
      "콜센터명": "제주콜센터",
      "콜센터번호": "TBD",
      "콜센터운영시간": "평일 09:00~18:00 (점심 12:00~13:00), 무인민원발급기 24시간"
    },
    {
      "emd_code": "SP-EMD-JUNGANG-SGP",
      "team_code": "general",
      "도이름": "제주특별자치도",
      "시이름": "서귀포시",
      "읍면동이름": "중앙동",
      "팀이름": "총무팀",
      "입력_문구": "민방위, 청소·환경정비, 이륜차 민원, 청사 관리 관련 접수·신청",
      "출력_문구": "민방위 훈련·청소환경정비 처리 결과, 청사 이용 안내",
      "콜센터명": "제주콜센터",
      "콜센터번호": "TBD",
      "콜센터운영시간": "평일 09:00~18:00 (점심 12:00~13:00), 무인민원발급기 24시간"
    },
    {
      "emd_code": "SP-EMD-JUNGANG-SGP",
      "team_code": "civil",
      "도이름": "제주특별자치도",
      "시이름": "서귀포시",
      "읍면동이름": "중앙동",
      "팀이름": "민원팀",
      "입력_문구": "주민등록등초본, 가족관계등록, 인감증명 등 제증명 발급 관련 접수·신청",
      "출력_문구": "즉시발급 증명서(등초본·인감증명 등)",
      "콜센터명": "제주콜센터",
      "콜센터번호": "TBD",
      "콜센터운영시간": "평일 09:00~18:00 (점심 12:00~13:00), 무인민원발급기 24시간"
    },
    {
      "emd_code": "SP-EMD-JUNGANG-SGP",
      "team_code": "welfare",
      "도이름": "제주특별자치도",
      "시이름": "서귀포시",
      "읍면동이름": "중앙동",
      "팀이름": "주민복지팀",
      "입력_문구": "기초생활수급·기초연금 접수, 보훈 접수(1차 접수, 최종 심사는 시청 소관) 관련 접수·신청",
      "출력_문구": "복지 신청 접수증(지급결정은 시청 복지위생국에서 확정)",
      "콜센터명": "제주콜센터",
      "콜센터번호": "TBD",
      "콜센터운영시간": "평일 09:00~18:00 (점심 12:00~13:00), 무인민원발급기 24시간"
    },
    {
      "emd_code": "SP-EMD-JUNGANG-SGP",
      "team_code": "outreach",
      "도이름": "제주특별자치도",
      "시이름": "서귀포시",
      "읍면동이름": "중앙동",
      "팀이름": "찾아가는복지팀",
      "입력_문구": "복지 사각지대 발굴, 방문 상담 관련 접수·신청",
      "출력_문구": "방문상담 결과, 복지서비스 연계",
      "콜센터명": "제주콜센터",
      "콜센터번호": "TBD",
      "콜센터운영시간": "평일 09:00~18:00 (점심 12:00~13:00), 무인민원발급기 24시간"
    },
    {
      "emd_code": "SP-EMD-CHEONJI",
      "team_code": "general",
      "도이름": "제주특별자치도",
      "시이름": "서귀포시",
      "읍면동이름": "천지동",
      "팀이름": "총무팀",
      "입력_문구": "민방위, 청소·환경정비, 이륜차 민원, 청사 관리 관련 접수·신청",
      "출력_문구": "민방위 훈련·청소환경정비 처리 결과, 청사 이용 안내",
      "콜센터명": "제주콜센터",
      "콜센터번호": "TBD",
      "콜센터운영시간": "평일 09:00~18:00 (점심 12:00~13:00), 무인민원발급기 24시간"
    },
    {
      "emd_code": "SP-EMD-CHEONJI",
      "team_code": "civil",
      "도이름": "제주특별자치도",
      "시이름": "서귀포시",
      "읍면동이름": "천지동",
      "팀이름": "민원팀",
      "입력_문구": "주민등록등초본, 가족관계등록, 인감증명 등 제증명 발급 관련 접수·신청",
      "출력_문구": "즉시발급 증명서(등초본·인감증명 등)",
      "콜센터명": "제주콜센터",
      "콜센터번호": "TBD",
      "콜센터운영시간": "평일 09:00~18:00 (점심 12:00~13:00), 무인민원발급기 24시간"
    },
    {
      "emd_code": "SP-EMD-CHEONJI",
      "team_code": "welfare",
      "도이름": "제주특별자치도",
      "시이름": "서귀포시",
      "읍면동이름": "천지동",
      "팀이름": "주민복지팀",
      "입력_문구": "기초생활수급·기초연금 접수, 보훈 접수(1차 접수, 최종 심사는 시청 소관) 관련 접수·신청",
      "출력_문구": "복지 신청 접수증(지급결정은 시청 복지위생국에서 확정)",
      "콜센터명": "제주콜센터",
      "콜센터번호": "TBD",
      "콜센터운영시간": "평일 09:00~18:00 (점심 12:00~13:00), 무인민원발급기 24시간"
    },
    {
      "emd_code": "SP-EMD-CHEONJI",
      "team_code": "outreach",
      "도이름": "제주특별자치도",
      "시이름": "서귀포시",
      "읍면동이름": "천지동",
      "팀이름": "찾아가는복지팀",
      "입력_문구": "복지 사각지대 발굴, 방문 상담 관련 접수·신청",
      "출력_문구": "방문상담 결과, 복지서비스 연계",
      "콜센터명": "제주콜센터",
      "콜센터번호": "TBD",
      "콜센터운영시간": "평일 09:00~18:00 (점심 12:00~13:00), 무인민원발급기 24시간"
    },
    {
      "emd_code": "SP-EMD-HYODON",
      "team_code": "general",
      "도이름": "제주특별자치도",
      "시이름": "서귀포시",
      "읍면동이름": "효돈동",
      "팀이름": "총무팀",
      "입력_문구": "민방위, 청소·환경정비, 이륜차 민원, 청사 관리 관련 접수·신청",
      "출력_문구": "민방위 훈련·청소환경정비 처리 결과, 청사 이용 안내",
      "콜센터명": "제주콜센터",
      "콜센터번호": "TBD",
      "콜센터운영시간": "평일 09:00~18:00 (점심 12:00~13:00), 무인민원발급기 24시간"
    },
    {
      "emd_code": "SP-EMD-HYODON",
      "team_code": "civil",
      "도이름": "제주특별자치도",
      "시이름": "서귀포시",
      "읍면동이름": "효돈동",
      "팀이름": "민원팀",
      "입력_문구": "주민등록등초본, 가족관계등록, 인감증명 등 제증명 발급 관련 접수·신청",
      "출력_문구": "즉시발급 증명서(등초본·인감증명 등)",
      "콜센터명": "제주콜센터",
      "콜센터번호": "TBD",
      "콜센터운영시간": "평일 09:00~18:00 (점심 12:00~13:00), 무인민원발급기 24시간"
    },
    {
      "emd_code": "SP-EMD-HYODON",
      "team_code": "welfare",
      "도이름": "제주특별자치도",
      "시이름": "서귀포시",
      "읍면동이름": "효돈동",
      "팀이름": "주민복지팀",
      "입력_문구": "기초생활수급·기초연금 접수, 보훈 접수(1차 접수, 최종 심사는 시청 소관) 관련 접수·신청",
      "출력_문구": "복지 신청 접수증(지급결정은 시청 복지위생국에서 확정)",
      "콜센터명": "제주콜센터",
      "콜센터번호": "TBD",
      "콜센터운영시간": "평일 09:00~18:00 (점심 12:00~13:00), 무인민원발급기 24시간"
    },
    {
      "emd_code": "SP-EMD-HYODON",
      "team_code": "outreach",
      "도이름": "제주특별자치도",
      "시이름": "서귀포시",
      "읍면동이름": "효돈동",
      "팀이름": "찾아가는복지팀",
      "입력_문구": "복지 사각지대 발굴, 방문 상담 관련 접수·신청",
      "출력_문구": "방문상담 결과, 복지서비스 연계",
      "콜센터명": "제주콜센터",
      "콜센터번호": "TBD",
      "콜센터운영시간": "평일 09:00~18:00 (점심 12:00~13:00), 무인민원발급기 24시간"
    },
    {
      "emd_code": "SP-EMD-YEONGCHEON",
      "team_code": "general",
      "도이름": "제주특별자치도",
      "시이름": "서귀포시",
      "읍면동이름": "영천동",
      "팀이름": "총무팀",
      "입력_문구": "민방위, 청소·환경정비, 이륜차 민원, 청사 관리 관련 접수·신청",
      "출력_문구": "민방위 훈련·청소환경정비 처리 결과, 청사 이용 안내",
      "콜센터명": "제주콜센터",
      "콜센터번호": "TBD",
      "콜센터운영시간": "평일 09:00~18:00 (점심 12:00~13:00), 무인민원발급기 24시간"
    },
    {
      "emd_code": "SP-EMD-YEONGCHEON",
      "team_code": "civil",
      "도이름": "제주특별자치도",
      "시이름": "서귀포시",
      "읍면동이름": "영천동",
      "팀이름": "민원팀",
      "입력_문구": "주민등록등초본, 가족관계등록, 인감증명 등 제증명 발급 관련 접수·신청",
      "출력_문구": "즉시발급 증명서(등초본·인감증명 등)",
      "콜센터명": "제주콜센터",
      "콜센터번호": "TBD",
      "콜센터운영시간": "평일 09:00~18:00 (점심 12:00~13:00), 무인민원발급기 24시간"
    },
    {
      "emd_code": "SP-EMD-YEONGCHEON",
      "team_code": "welfare",
      "도이름": "제주특별자치도",
      "시이름": "서귀포시",
      "읍면동이름": "영천동",
      "팀이름": "주민복지팀",
      "입력_문구": "기초생활수급·기초연금 접수, 보훈 접수(1차 접수, 최종 심사는 시청 소관) 관련 접수·신청",
      "출력_문구": "복지 신청 접수증(지급결정은 시청 복지위생국에서 확정)",
      "콜센터명": "제주콜센터",
      "콜센터번호": "TBD",
      "콜센터운영시간": "평일 09:00~18:00 (점심 12:00~13:00), 무인민원발급기 24시간"
    },
    {
      "emd_code": "SP-EMD-YEONGCHEON",
      "team_code": "outreach",
      "도이름": "제주특별자치도",
      "시이름": "서귀포시",
      "읍면동이름": "영천동",
      "팀이름": "찾아가는복지팀",
      "입력_문구": "복지 사각지대 발굴, 방문 상담 관련 접수·신청",
      "출력_문구": "방문상담 결과, 복지서비스 연계",
      "콜센터명": "제주콜센터",
      "콜센터번호": "TBD",
      "콜센터운영시간": "평일 09:00~18:00 (점심 12:00~13:00), 무인민원발급기 24시간"
    },
    {
      "emd_code": "SP-EMD-DONGHONG",
      "team_code": "general",
      "도이름": "제주특별자치도",
      "시이름": "서귀포시",
      "읍면동이름": "동홍동",
      "팀이름": "총무팀",
      "입력_문구": "민방위, 청소·환경정비, 이륜차 민원, 청사 관리 관련 접수·신청",
      "출력_문구": "민방위 훈련·청소환경정비 처리 결과, 청사 이용 안내",
      "콜센터명": "제주콜센터",
      "콜센터번호": "TBD",
      "콜센터운영시간": "평일 09:00~18:00 (점심 12:00~13:00), 무인민원발급기 24시간"
    },
    {
      "emd_code": "SP-EMD-DONGHONG",
      "team_code": "civil",
      "도이름": "제주특별자치도",
      "시이름": "서귀포시",
      "읍면동이름": "동홍동",
      "팀이름": "민원팀",
      "입력_문구": "주민등록등초본, 가족관계등록, 인감증명 등 제증명 발급 관련 접수·신청",
      "출력_문구": "즉시발급 증명서(등초본·인감증명 등)",
      "콜센터명": "제주콜센터",
      "콜센터번호": "TBD",
      "콜센터운영시간": "평일 09:00~18:00 (점심 12:00~13:00), 무인민원발급기 24시간"
    },
    {
      "emd_code": "SP-EMD-DONGHONG",
      "team_code": "welfare",
      "도이름": "제주특별자치도",
      "시이름": "서귀포시",
      "읍면동이름": "동홍동",
      "팀이름": "주민복지팀",
      "입력_문구": "기초생활수급·기초연금 접수, 보훈 접수(1차 접수, 최종 심사는 시청 소관) 관련 접수·신청",
      "출력_문구": "복지 신청 접수증(지급결정은 시청 복지위생국에서 확정)",
      "콜센터명": "제주콜센터",
      "콜센터번호": "TBD",
      "콜센터운영시간": "평일 09:00~18:00 (점심 12:00~13:00), 무인민원발급기 24시간"
    },
    {
      "emd_code": "SP-EMD-DONGHONG",
      "team_code": "outreach",
      "도이름": "제주특별자치도",
      "시이름": "서귀포시",
      "읍면동이름": "동홍동",
      "팀이름": "찾아가는복지팀",
      "입력_문구": "복지 사각지대 발굴, 방문 상담 관련 접수·신청",
      "출력_문구": "방문상담 결과, 복지서비스 연계",
      "콜센터명": "제주콜센터",
      "콜센터번호": "TBD",
      "콜센터운영시간": "평일 09:00~18:00 (점심 12:00~13:00), 무인민원발급기 24시간"
    },
    {
      "emd_code": "SP-EMD-SEOHONG",
      "team_code": "general",
      "도이름": "제주특별자치도",
      "시이름": "서귀포시",
      "읍면동이름": "서홍동",
      "팀이름": "총무팀",
      "입력_문구": "민방위, 청소·환경정비, 이륜차 민원, 청사 관리 관련 접수·신청",
      "출력_문구": "민방위 훈련·청소환경정비 처리 결과, 청사 이용 안내",
      "콜센터명": "제주콜센터",
      "콜센터번호": "TBD",
      "콜센터운영시간": "평일 09:00~18:00 (점심 12:00~13:00), 무인민원발급기 24시간"
    },
    {
      "emd_code": "SP-EMD-SEOHONG",
      "team_code": "civil",
      "도이름": "제주특별자치도",
      "시이름": "서귀포시",
      "읍면동이름": "서홍동",
      "팀이름": "민원팀",
      "입력_문구": "주민등록등초본, 가족관계등록, 인감증명 등 제증명 발급 관련 접수·신청",
      "출력_문구": "즉시발급 증명서(등초본·인감증명 등)",
      "콜센터명": "제주콜센터",
      "콜센터번호": "TBD",
      "콜센터운영시간": "평일 09:00~18:00 (점심 12:00~13:00), 무인민원발급기 24시간"
    },
    {
      "emd_code": "SP-EMD-SEOHONG",
      "team_code": "welfare",
      "도이름": "제주특별자치도",
      "시이름": "서귀포시",
      "읍면동이름": "서홍동",
      "팀이름": "주민복지팀",
      "입력_문구": "기초생활수급·기초연금 접수, 보훈 접수(1차 접수, 최종 심사는 시청 소관) 관련 접수·신청",
      "출력_문구": "복지 신청 접수증(지급결정은 시청 복지위생국에서 확정)",
      "콜센터명": "제주콜센터",
      "콜센터번호": "TBD",
      "콜센터운영시간": "평일 09:00~18:00 (점심 12:00~13:00), 무인민원발급기 24시간"
    },
    {
      "emd_code": "SP-EMD-SEOHONG",
      "team_code": "outreach",
      "도이름": "제주특별자치도",
      "시이름": "서귀포시",
      "읍면동이름": "서홍동",
      "팀이름": "찾아가는복지팀",
      "입력_문구": "복지 사각지대 발굴, 방문 상담 관련 접수·신청",
      "출력_문구": "방문상담 결과, 복지서비스 연계",
      "콜센터명": "제주콜센터",
      "콜센터번호": "TBD",
      "콜센터운영시간": "평일 09:00~18:00 (점심 12:00~13:00), 무인민원발급기 24시간"
    },
    {
      "emd_code": "SP-EMD-DAERYUN",
      "team_code": "general",
      "도이름": "제주특별자치도",
      "시이름": "서귀포시",
      "읍면동이름": "대륜동",
      "팀이름": "총무팀",
      "입력_문구": "민방위, 청소·환경정비, 이륜차 민원, 청사 관리 관련 접수·신청",
      "출력_문구": "민방위 훈련·청소환경정비 처리 결과, 청사 이용 안내",
      "콜센터명": "제주콜센터",
      "콜센터번호": "TBD",
      "콜센터운영시간": "평일 09:00~18:00 (점심 12:00~13:00), 무인민원발급기 24시간"
    },
    {
      "emd_code": "SP-EMD-DAERYUN",
      "team_code": "civil",
      "도이름": "제주특별자치도",
      "시이름": "서귀포시",
      "읍면동이름": "대륜동",
      "팀이름": "민원팀",
      "입력_문구": "주민등록등초본, 가족관계등록, 인감증명 등 제증명 발급 관련 접수·신청",
      "출력_문구": "즉시발급 증명서(등초본·인감증명 등)",
      "콜센터명": "제주콜센터",
      "콜센터번호": "TBD",
      "콜센터운영시간": "평일 09:00~18:00 (점심 12:00~13:00), 무인민원발급기 24시간"
    },
    {
      "emd_code": "SP-EMD-DAERYUN",
      "team_code": "welfare",
      "도이름": "제주특별자치도",
      "시이름": "서귀포시",
      "읍면동이름": "대륜동",
      "팀이름": "주민복지팀",
      "입력_문구": "기초생활수급·기초연금 접수, 보훈 접수(1차 접수, 최종 심사는 시청 소관) 관련 접수·신청",
      "출력_문구": "복지 신청 접수증(지급결정은 시청 복지위생국에서 확정)",
      "콜센터명": "제주콜센터",
      "콜센터번호": "TBD",
      "콜센터운영시간": "평일 09:00~18:00 (점심 12:00~13:00), 무인민원발급기 24시간"
    },
    {
      "emd_code": "SP-EMD-DAERYUN",
      "team_code": "outreach",
      "도이름": "제주특별자치도",
      "시이름": "서귀포시",
      "읍면동이름": "대륜동",
      "팀이름": "찾아가는복지팀",
      "입력_문구": "복지 사각지대 발굴, 방문 상담 관련 접수·신청",
      "출력_문구": "방문상담 결과, 복지서비스 연계",
      "콜센터명": "제주콜센터",
      "콜센터번호": "TBD",
      "콜센터운영시간": "평일 09:00~18:00 (점심 12:00~13:00), 무인민원발급기 24시간"
    },
    {
      "emd_code": "SP-EMD-DAECHEON",
      "team_code": "general",
      "도이름": "제주특별자치도",
      "시이름": "서귀포시",
      "읍면동이름": "대천동",
      "팀이름": "총무팀",
      "입력_문구": "민방위, 청소·환경정비, 이륜차 민원, 청사 관리 관련 접수·신청",
      "출력_문구": "민방위 훈련·청소환경정비 처리 결과, 청사 이용 안내",
      "콜센터명": "제주콜센터",
      "콜센터번호": "TBD",
      "콜센터운영시간": "평일 09:00~18:00 (점심 12:00~13:00), 무인민원발급기 24시간"
    },
    {
      "emd_code": "SP-EMD-DAECHEON",
      "team_code": "civil",
      "도이름": "제주특별자치도",
      "시이름": "서귀포시",
      "읍면동이름": "대천동",
      "팀이름": "민원팀",
      "입력_문구": "주민등록등초본, 가족관계등록, 인감증명 등 제증명 발급 관련 접수·신청",
      "출력_문구": "즉시발급 증명서(등초본·인감증명 등)",
      "콜센터명": "제주콜센터",
      "콜센터번호": "TBD",
      "콜센터운영시간": "평일 09:00~18:00 (점심 12:00~13:00), 무인민원발급기 24시간"
    },
    {
      "emd_code": "SP-EMD-DAECHEON",
      "team_code": "welfare",
      "도이름": "제주특별자치도",
      "시이름": "서귀포시",
      "읍면동이름": "대천동",
      "팀이름": "주민복지팀",
      "입력_문구": "기초생활수급·기초연금 접수, 보훈 접수(1차 접수, 최종 심사는 시청 소관) 관련 접수·신청",
      "출력_문구": "복지 신청 접수증(지급결정은 시청 복지위생국에서 확정)",
      "콜센터명": "제주콜센터",
      "콜센터번호": "TBD",
      "콜센터운영시간": "평일 09:00~18:00 (점심 12:00~13:00), 무인민원발급기 24시간"
    },
    {
      "emd_code": "SP-EMD-DAECHEON",
      "team_code": "outreach",
      "도이름": "제주특별자치도",
      "시이름": "서귀포시",
      "읍면동이름": "대천동",
      "팀이름": "찾아가는복지팀",
      "입력_문구": "복지 사각지대 발굴, 방문 상담 관련 접수·신청",
      "출력_문구": "방문상담 결과, 복지서비스 연계",
      "콜센터명": "제주콜센터",
      "콜센터번호": "TBD",
      "콜센터운영시간": "평일 09:00~18:00 (점심 12:00~13:00), 무인민원발급기 24시간"
    },
    {
      "emd_code": "SP-EMD-JUNGMUN",
      "team_code": "general",
      "도이름": "제주특별자치도",
      "시이름": "서귀포시",
      "읍면동이름": "중문동",
      "팀이름": "총무팀",
      "입력_문구": "민방위, 청소·환경정비, 이륜차 민원, 청사 관리 관련 접수·신청",
      "출력_문구": "민방위 훈련·청소환경정비 처리 결과, 청사 이용 안내",
      "콜센터명": "제주콜센터",
      "콜센터번호": "TBD",
      "콜센터운영시간": "평일 09:00~18:00 (점심 12:00~13:00), 무인민원발급기 24시간"
    },
    {
      "emd_code": "SP-EMD-JUNGMUN",
      "team_code": "civil",
      "도이름": "제주특별자치도",
      "시이름": "서귀포시",
      "읍면동이름": "중문동",
      "팀이름": "민원팀",
      "입력_문구": "주민등록등초본, 가족관계등록, 인감증명 등 제증명 발급 관련 접수·신청",
      "출력_문구": "즉시발급 증명서(등초본·인감증명 등)",
      "콜센터명": "제주콜센터",
      "콜센터번호": "TBD",
      "콜센터운영시간": "평일 09:00~18:00 (점심 12:00~13:00), 무인민원발급기 24시간"
    },
    {
      "emd_code": "SP-EMD-JUNGMUN",
      "team_code": "welfare",
      "도이름": "제주특별자치도",
      "시이름": "서귀포시",
      "읍면동이름": "중문동",
      "팀이름": "주민복지팀",
      "입력_문구": "기초생활수급·기초연금 접수, 보훈 접수(1차 접수, 최종 심사는 시청 소관) 관련 접수·신청",
      "출력_문구": "복지 신청 접수증(지급결정은 시청 복지위생국에서 확정)",
      "콜센터명": "제주콜센터",
      "콜센터번호": "TBD",
      "콜센터운영시간": "평일 09:00~18:00 (점심 12:00~13:00), 무인민원발급기 24시간"
    },
    {
      "emd_code": "SP-EMD-JUNGMUN",
      "team_code": "outreach",
      "도이름": "제주특별자치도",
      "시이름": "서귀포시",
      "읍면동이름": "중문동",
      "팀이름": "찾아가는복지팀",
      "입력_문구": "복지 사각지대 발굴, 방문 상담 관련 접수·신청",
      "출력_문구": "방문상담 결과, 복지서비스 연계",
      "콜센터명": "제주콜센터",
      "콜센터번호": "TBD",
      "콜센터운영시간": "평일 09:00~18:00 (점심 12:00~13:00), 무인민원발급기 24시간"
    },
    {
      "emd_code": "SP-EMD-YERAE",
      "team_code": "general",
      "도이름": "제주특별자치도",
      "시이름": "서귀포시",
      "읍면동이름": "예래동",
      "팀이름": "총무팀",
      "입력_문구": "민방위, 청소·환경정비, 이륜차 민원, 청사 관리 관련 접수·신청",
      "출력_문구": "민방위 훈련·청소환경정비 처리 결과, 청사 이용 안내",
      "콜센터명": "제주콜센터",
      "콜센터번호": "TBD",
      "콜센터운영시간": "평일 09:00~18:00 (점심 12:00~13:00), 무인민원발급기 24시간"
    },
    {
      "emd_code": "SP-EMD-YERAE",
      "team_code": "civil",
      "도이름": "제주특별자치도",
      "시이름": "서귀포시",
      "읍면동이름": "예래동",
      "팀이름": "민원팀",
      "입력_문구": "주민등록등초본, 가족관계등록, 인감증명 등 제증명 발급 관련 접수·신청",
      "출력_문구": "즉시발급 증명서(등초본·인감증명 등)",
      "콜센터명": "제주콜센터",
      "콜센터번호": "TBD",
      "콜센터운영시간": "평일 09:00~18:00 (점심 12:00~13:00), 무인민원발급기 24시간"
    },
    {
      "emd_code": "SP-EMD-YERAE",
      "team_code": "welfare",
      "도이름": "제주특별자치도",
      "시이름": "서귀포시",
      "읍면동이름": "예래동",
      "팀이름": "주민복지팀",
      "입력_문구": "기초생활수급·기초연금 접수, 보훈 접수(1차 접수, 최종 심사는 시청 소관) 관련 접수·신청",
      "출력_문구": "복지 신청 접수증(지급결정은 시청 복지위생국에서 확정)",
      "콜센터명": "제주콜센터",
      "콜센터번호": "TBD",
      "콜센터운영시간": "평일 09:00~18:00 (점심 12:00~13:00), 무인민원발급기 24시간"
    },
    {
      "emd_code": "SP-EMD-YERAE",
      "team_code": "outreach",
      "도이름": "제주특별자치도",
      "시이름": "서귀포시",
      "읍면동이름": "예래동",
      "팀이름": "찾아가는복지팀",
      "입력_문구": "복지 사각지대 발굴, 방문 상담 관련 접수·신청",
      "출력_문구": "방문상담 결과, 복지서비스 연계",
      "콜센터명": "제주콜센터",
      "콜센터번호": "TBD",
      "콜센터운영시간": "평일 09:00~18:00 (점심 12:00~13:00), 무인민원발급기 24시간"
    },
    {
      "emd_code": "SP-EMD-HALLIM",
      "team_code": "general",
      "도이름": "제주특별자치도",
      "시이름": "제주시",
      "읍면동이름": "한림읍",
      "팀이름": "총무팀",
      "입력_문구": "민방위, 청소·환경정비, 이륜차 민원, 청사 관리 관련 접수·신청",
      "출력_문구": "민방위 훈련·청소환경정비 처리 결과, 청사 이용 안내",
      "콜센터명": "제주콜센터",
      "콜센터번호": "064-728-4171",
      "콜센터운영시간": "평일 09:00~18:00 (점심 12:00~13:00), 무인민원발급기 24시간"
    },
    {
      "emd_code": "SP-EMD-HALLIM",
      "team_code": "civil",
      "도이름": "제주특별자치도",
      "시이름": "제주시",
      "읍면동이름": "한림읍",
      "팀이름": "민원팀",
      "입력_문구": "주민등록등초본, 가족관계등록, 인감증명 등 제증명 발급 관련 접수·신청",
      "출력_문구": "즉시발급 증명서(등초본·인감증명 등)",
      "콜센터명": "제주콜센터",
      "콜센터번호": "064-728-4171",
      "콜센터운영시간": "평일 09:00~18:00 (점심 12:00~13:00), 무인민원발급기 24시간"
    },
    {
      "emd_code": "SP-EMD-HALLIM",
      "team_code": "industry",
      "도이름": "제주특별자치도",
      "시이름": "제주시",
      "읍면동이름": "한림읍",
      "팀이름": "산업팀",
      "입력_문구": "농업경영체 등록, 영농지원(마늘·양배추 등 밭작물), 축산 관련(금악리 목장지대), 어업·항포구 관련(한림항·옹포리) 관련 접수·신청",
      "출력_문구": "접수증(최종 등록·지원 결정은 시청 소관 부서에서 확정)",
      "콜센터명": "제주콜센터",
      "콜센터번호": "064-728-4171",
      "콜센터운영시간": "평일 09:00~18:00 (점심 12:00~13:00), 무인민원발급기 24시간"
    },
    {
      "emd_code": "SP-EMD-HALLIM",
      "team_code": "welfare",
      "도이름": "제주특별자치도",
      "시이름": "제주시",
      "읍면동이름": "한림읍",
      "팀이름": "주민복지팀",
      "입력_문구": "기초생활수급·기초연금 접수, 보훈 접수(1차 접수, 최종 심사는 시청 복지위생국) 관련 접수·신청",
      "출력_문구": "복지 신청 접수증(지급결정은 시청 복지위생국에서 확정)",
      "콜센터명": "제주콜센터",
      "콜센터번호": "064-728-4171",
      "콜센터운영시간": "평일 09:00~18:00 (점심 12:00~13:00), 무인민원발급기 24시간"
    },
    {
      "emd_code": "SP-EMD-HALLIM",
      "team_code": "outreach",
      "도이름": "제주특별자치도",
      "시이름": "제주시",
      "읍면동이름": "한림읍",
      "팀이름": "찾아가는복지팀",
      "입력_문구": "복지 사각지대 발굴, 방문 상담 관련 접수·신청",
      "출력_문구": "방문상담 결과, 복지서비스 연계",
      "콜센터명": "제주콜센터",
      "콜센터번호": "064-728-4171",
      "콜센터운영시간": "평일 09:00~18:00 (점심 12:00~13:00), 무인민원발급기 24시간"
    }
  ]
}